[
  {
    "info": {
      "name": "titlebar3",
      "type": "titlebar"
    },
    "use": "<%- include(common_component + '/titlebar/titlebar3.ejs')%>",
    "ejs": " <div class=\"border-b border-solid border-gray-300\">\n   <span class=\"pb-1 inline-block w-fit mb-[-1px] border-b-2 border-solid border-red-400 font-[600]\">\n     <%=titlebar%>\n   </span>\n </div>\n",
    "html": " <div class=\"border-b border-solid border-gray-300\">\n   <span class=\"pb-1 inline-block w-fit mb-[-1px] border-b-2 border-solid border-red-400 font-[600]\">\n     Popular News\n   </span>\n </div>\n"
  },
  {
    "info": {
      "name": "titlebar2",
      "type": "titlebar"
    },
    "use": "<%- include(common_component + '/titlebar/titlebar2.ejs')%>",
    "ejs": "<div class=\"flex h-5\">\n  <span class=\"border-l-[5px] border-solid border-orange-400 pl-3 text-2xl text-orange-400 font-bold flex items-center\">\n    <%=titlebar%>\n  </span>\n</div>\n",
    "html": "<div class=\"flex h-5\">\n  <span class=\"border-l-[5px] border-solid border-orange-400 pl-3 text-2xl text-orange-400 font-bold flex items-center\">\n    Popular News\n  </span>\n</div>\n"
  },
  {
    "info": {
      "name": "titlebar1",
      "type": "titlebar"
    },
    "use": "<%- include(common_component + '/titlebar/titlebar1.ejs')%>",
    "ejs": "<div class=\"flex h-14 bg-gray-200\">\n  <span class=\"bg-orange-400 px-5 text-2xl text-white font-bold flex items-center\">\n    <%=titlebar%>\n  </span>\n</div>\n",
    "html": "<div class=\"flex h-14 bg-gray-200\">\n  <span class=\"bg-orange-400 px-5 text-2xl text-white font-bold flex items-center\">\n    Popular News\n  </span>\n</div>\n"
  },
  {
    "info": {
      "name": "layout3",
      "type": "layout"
    },
    "use": "<%- include(common_component + '/layout/layout3.ejs')%>",
    "ejs": "\n<div class=\"grid sm:grid-cols-7 gap-4\">\n    <div class=\"sm:col-span-3 bg-blue-100 h-40\"></div>\n    <div class=\"sm:col-start-4 sm:col-span-2 bg-blue-100 h-40\"></div>\n    <div class=\"sm:col-start-6 sm:col-span-2 bg-blue-100 h-40\"></div>\n</div>\n",
    "html": "\n<div class=\"grid sm:grid-cols-7 gap-4\">\n    <div class=\"sm:col-span-3 bg-blue-100 h-40\"></div>\n    <div class=\"sm:col-start-4 sm:col-span-2 bg-blue-100 h-40\"></div>\n    <div class=\"sm:col-start-6 sm:col-span-2 bg-blue-100 h-40\"></div>\n</div>\n"
  },
  {
    "info": {
      "name": "layout2",
      "type": "layout"
    },
    "use": "<%- include(common_component + '/layout/layout2.ejs')%>",
    "ejs": "<div class=\"grid sm:grid-cols-5 gap-4\">\n  <div class=\"sm:col-span-4 bg-blue-100 h-40\"></div>\n  <div class=\"sm:col-start-5 bg-blue-100 h-40\"></div>\n</div>\n",
    "html": "<div class=\"grid sm:grid-cols-5 gap-4\">\n  <div class=\"sm:col-span-4 bg-blue-100 h-40\"></div>\n  <div class=\"sm:col-start-5 bg-blue-100 h-40\"></div>\n</div>\n"
  },
  {
    "info": {
      "name": "layout1",
      "type": "layout"
    },
    "use": "<%- include(common_component + '/layout/layout1.ejs')%>",
    "ejs": "<div class=\"grid grid-cols-1 md:grid-cols-2 xl:grid-cols-3 gap-2\">\n  <div class=\"bg-blue-100 h-40\">\n  </div>\n  <div class=\"bg-blue-100  h-40\">\n  </div>\n  <div class=\"bg-blue-100  h-40\">\n  </div>\n</div>\n",
    "html": "<div class=\"grid grid-cols-1 md:grid-cols-2 xl:grid-cols-3 gap-2\">\n  <div class=\"bg-blue-100 h-40\">\n  </div>\n  <div class=\"bg-blue-100  h-40\">\n  </div>\n  <div class=\"bg-blue-100  h-40\">\n  </div>\n</div>\n"
  },
  {
    "info": {
      "name": "header2",
      "type": "header"
    },
    "use": "<%- include(common_component + '/header/header2.ejs')%>",
    "ejs": "<header class=\"bg-white\">\n  <nav class=\"mx-auto flex max-w-7xl items-center justify-between p-6 lg:px-8\" aria-label=\"Global\">\n    <div class=\"flex lg:flex-1\">\n      <a href=\"#\" class=\"-m-1.5 p-1.5\">\n        <span class=\"sr-only\">Your Company</span>\n        <img class=\"h-8 w-auto\" src=\"https://tailwindui.com/img/logos/mark.svg?color=indigo&shade=600\" alt=\"\">\n      </a>\n    </div>\n    <div class=\"flex lg:hidden\">\n      <button type=\"button\" class=\"-m-2.5 inline-flex items-center justify-center rounded-md p-2.5 text-gray-700\">\n        <span class=\"sr-only\">Open main menu</span>\n        <svg class=\"h-6 w-6\" fill=\"none\" viewBox=\"0 0 24 24\" stroke-width=\"1.5\" stroke=\"currentColor\" aria-hidden=\"true\">\n          <path stroke-linecap=\"round\" stroke-linejoin=\"round\" d=\"M3.75 6.75h16.5M3.75 12h16.5m-16.5 5.25h16.5\" />\n        </svg>\n      </button>\n    </div>\n    <div class=\"hidden lg:flex lg:gap-x-12\">\n      <div class=\"relative\">\n        <button type=\"button\" class=\"flex items-center gap-x-1 text-sm font-semibold leading-6 text-gray-900\" aria-expanded=\"false\">\n          Product\n          <svg class=\"h-5 w-5 flex-none text-gray-400\" viewBox=\"0 0 20 20\" fill=\"currentColor\" aria-hidden=\"true\">\n            <path fill-rule=\"evenodd\" d=\"M5.23 7.21a.75.75 0 011.06.02L10 11.168l3.71-3.938a.75.75 0 111.08 1.04l-4.25 4.5a.75.75 0 01-1.08 0l-4.25-4.5a.75.75 0 01.02-1.06z\" clip-rule=\"evenodd\" />\n          </svg>\n        </button>\n\n        <!--\n          'Product' flyout menu, show/hide based on flyout menu state.\n\n          Entering: \"transition ease-out duration-200\"\n            From: \"opacity-0 translate-y-1\"\n            To: \"opacity-100 translate-y-0\"\n          Leaving: \"transition ease-in duration-150\"\n            From: \"opacity-100 translate-y-0\"\n            To: \"opacity-0 translate-y-1\"\n        -->\n        <div class=\"absolute -left-8 top-full z-10 mt-3 w-screen max-w-md overflow-hidden rounded-3xl bg-white shadow-lg ring-1 ring-gray-900/5\">\n          <div class=\"p-4\">\n            <div class=\"group relative flex items-center gap-x-6 rounded-lg p-4 text-sm leading-6 hover:bg-gray-50\">\n              <div class=\"flex h-11 w-11 flex-none items-center justify-center rounded-lg bg-gray-50 group-hover:bg-white\">\n                <svg class=\"h-6 w-6 text-gray-600 group-hover:text-indigo-600\" fill=\"none\" viewBox=\"0 0 24 24\" stroke-width=\"1.5\" stroke=\"currentColor\" aria-hidden=\"true\">\n                  <path stroke-linecap=\"round\" stroke-linejoin=\"round\" d=\"M10.5 6a7.5 7.5 0 107.5 7.5h-7.5V6z\" />\n                  <path stroke-linecap=\"round\" stroke-linejoin=\"round\" d=\"M13.5 10.5H21A7.5 7.5 0 0013.5 3v7.5z\" />\n                </svg>\n              </div>\n              <div class=\"flex-auto\">\n                <a href=\"#\" class=\"block font-semibold text-gray-900\">\n                  Analytics\n                  <span class=\"absolute inset-0\"></span>\n                </a>\n                <p class=\"mt-1 text-gray-600\">Get a better understanding of your traffic</p>\n              </div>\n            </div>\n            <div class=\"group relative flex items-center gap-x-6 rounded-lg p-4 text-sm leading-6 hover:bg-gray-50\">\n              <div class=\"flex h-11 w-11 flex-none items-center justify-center rounded-lg bg-gray-50 group-hover:bg-white\">\n                <svg class=\"h-6 w-6 text-gray-600 group-hover:text-indigo-600\" fill=\"none\" viewBox=\"0 0 24 24\" stroke-width=\"1.5\" stroke=\"currentColor\" aria-hidden=\"true\">\n                  <path stroke-linecap=\"round\" stroke-linejoin=\"round\" d=\"M15.042 21.672L13.684 16.6m0 0l-2.51 2.225.569-9.47 5.227 7.917-3.286-.672zM12 2.25V4.5m5.834.166l-1.591 1.591M20.25 10.5H18M7.757 14.743l-1.59 1.59M6 10.5H3.75m4.007-4.243l-1.59-1.59\" />\n                </svg>\n              </div>\n              <div class=\"flex-auto\">\n                <a href=\"#\" class=\"block font-semibold text-gray-900\">\n                  Engagement\n                  <span class=\"absolute inset-0\"></span>\n                </a>\n                <p class=\"mt-1 text-gray-600\">Speak directly to your customers</p>\n              </div>\n            </div>\n            <div class=\"group relative flex items-center gap-x-6 rounded-lg p-4 text-sm leading-6 hover:bg-gray-50\">\n              <div class=\"flex h-11 w-11 flex-none items-center justify-center rounded-lg bg-gray-50 group-hover:bg-white\">\n                <svg class=\"h-6 w-6 text-gray-600 group-hover:text-indigo-600\" fill=\"none\" viewBox=\"0 0 24 24\" stroke-width=\"1.5\" stroke=\"currentColor\" aria-hidden=\"true\">\n                  <path stroke-linecap=\"round\" stroke-linejoin=\"round\" d=\"M7.864 4.243A7.5 7.5 0 0119.5 10.5c0 2.92-.556 5.709-1.568 8.268M5.742 6.364A7.465 7.465 0 004.5 10.5a7.464 7.464 0 01-1.15 3.993m1.989 3.559A11.209 11.209 0 008.25 10.5a3.75 3.75 0 117.5 0c0 .527-.021 1.049-.064 1.565M12 10.5a14.94 14.94 0 01-3.6 9.75m6.633-4.596a18.666 18.666 0 01-2.485 5.33\" />\n                </svg>\n              </div>\n              <div class=\"flex-auto\">\n                <a href=\"#\" class=\"block font-semibold text-gray-900\">\n                  Security\n                  <span class=\"absolute inset-0\"></span>\n                </a>\n                <p class=\"mt-1 text-gray-600\">Your customers’ data will be safe and secure</p>\n              </div>\n            </div>\n            <div class=\"group relative flex items-center gap-x-6 rounded-lg p-4 text-sm leading-6 hover:bg-gray-50\">\n              <div class=\"flex h-11 w-11 flex-none items-center justify-center rounded-lg bg-gray-50 group-hover:bg-white\">\n                <svg class=\"h-6 w-6 text-gray-600 group-hover:text-indigo-600\" fill=\"none\" viewBox=\"0 0 24 24\" stroke-width=\"1.5\" stroke=\"currentColor\" aria-hidden=\"true\">\n                  <path stroke-linecap=\"round\" stroke-linejoin=\"round\" d=\"M13.5 16.875h3.375m0 0h3.375m-3.375 0V13.5m0 3.375v3.375M6 10.5h2.25a2.25 2.25 0 002.25-2.25V6a2.25 2.25 0 00-2.25-2.25H6A2.25 2.25 0 003.75 6v2.25A2.25 2.25 0 006 10.5zm0 9.75h2.25A2.25 2.25 0 0010.5 18v-2.25a2.25 2.25 0 00-2.25-2.25H6a2.25 2.25 0 00-2.25 2.25V18A2.25 2.25 0 006 20.25zm9.75-9.75H18a2.25 2.25 0 002.25-2.25V6A2.25 2.25 0 0018 3.75h-2.25A2.25 2.25 0 0013.5 6v2.25a2.25 2.25 0 002.25 2.25z\" />\n                </svg>\n              </div>\n              <div class=\"flex-auto\">\n                <a href=\"#\" class=\"block font-semibold text-gray-900\">\n                  Integrations\n                  <span class=\"absolute inset-0\"></span>\n                </a>\n                <p class=\"mt-1 text-gray-600\">Connect with third-party tools</p>\n              </div>\n            </div>\n            <div class=\"group relative flex items-center gap-x-6 rounded-lg p-4 text-sm leading-6 hover:bg-gray-50\">\n              <div class=\"flex h-11 w-11 flex-none items-center justify-center rounded-lg bg-gray-50 group-hover:bg-white\">\n                <svg class=\"h-6 w-6 text-gray-600 group-hover:text-indigo-600\" fill=\"none\" viewBox=\"0 0 24 24\" stroke-width=\"1.5\" stroke=\"currentColor\" aria-hidden=\"true\">\n                  <path stroke-linecap=\"round\" stroke-linejoin=\"round\" d=\"M16.023 9.348h4.992v-.001M2.985 19.644v-4.992m0 0h4.992m-4.993 0l3.181 3.183a8.25 8.25 0 0013.803-3.7M4.031 9.865a8.25 8.25 0 0113.803-3.7l3.181 3.182m0-4.991v4.99\" />\n                </svg>\n              </div>\n              <div class=\"flex-auto\">\n                <a href=\"#\" class=\"block font-semibold text-gray-900\">\n                  Automations\n                  <span class=\"absolute inset-0\"></span>\n                </a>\n                <p class=\"mt-1 text-gray-600\">Build strategic funnels that will convert</p>\n              </div>\n            </div>\n          </div>\n          <div class=\"grid grid-cols-2 divide-x divide-gray-900/5 bg-gray-50\">\n            <a href=\"#\" class=\"flex items-center justify-center gap-x-2.5 p-3 text-sm font-semibold leading-6 text-gray-900 hover:bg-gray-100\">\n              <svg class=\"h-5 w-5 flex-none text-gray-400\" viewBox=\"0 0 20 20\" fill=\"currentColor\" aria-hidden=\"true\">\n                <path fill-rule=\"evenodd\" d=\"M2 10a8 8 0 1116 0 8 8 0 01-16 0zm6.39-2.908a.75.75 0 01.766.027l3.5 2.25a.75.75 0 010 1.262l-3.5 2.25A.75.75 0 018 12.25v-4.5a.75.75 0 01.39-.658z\" clip-rule=\"evenodd\" />\n              </svg>\n              Watch demo\n            </a>\n            <a href=\"#\" class=\"flex items-center justify-center gap-x-2.5 p-3 text-sm font-semibold leading-6 text-gray-900 hover:bg-gray-100\">\n              <svg class=\"h-5 w-5 flex-none text-gray-400\" viewBox=\"0 0 20 20\" fill=\"currentColor\" aria-hidden=\"true\">\n                <path fill-rule=\"evenodd\" d=\"M2 3.5A1.5 1.5 0 013.5 2h1.148a1.5 1.5 0 011.465 1.175l.716 3.223a1.5 1.5 0 01-1.052 1.767l-.933.267c-.41.117-.643.555-.48.95a11.542 11.542 0 006.254 6.254c.395.163.833-.07.95-.48l.267-.933a1.5 1.5 0 011.767-1.052l3.223.716A1.5 1.5 0 0118 15.352V16.5a1.5 1.5 0 01-1.5 1.5H15c-1.149 0-2.263-.15-3.326-.43A13.022 13.022 0 012.43 8.326 13.019 13.019 0 012 5V3.5z\" clip-rule=\"evenodd\" />\n              </svg>\n              Contact sales\n            </a>\n          </div>\n        </div>\n      </div>\n\n      <a href=\"#\" class=\"text-sm font-semibold leading-6 text-gray-900\">Features</a>\n      <a href=\"#\" class=\"text-sm font-semibold leading-6 text-gray-900\">Marketplace</a>\n      <a href=\"#\" class=\"text-sm font-semibold leading-6 text-gray-900\">Company</a>\n    </div>\n    <div class=\"hidden lg:flex lg:flex-1 lg:justify-end\">\n      <a href=\"#\" class=\"text-sm font-semibold leading-6 text-gray-900\">Log in <span aria-hidden=\"true\">&rarr;</span></a>\n    </div>\n  </nav>\n  <!-- Mobile menu, show/hide based on menu open state. -->\n  <div class=\"lg:hidden\" role=\"dialog\" aria-modal=\"true\">\n    <!-- Background backdrop, show/hide based on slide-over state. -->\n    <div class=\"fixed inset-0 z-10\"></div>\n    <div class=\"fixed inset-y-0 right-0 z-10 w-full overflow-y-auto bg-white px-6 py-6 sm:max-w-sm sm:ring-1 sm:ring-gray-900/10\">\n      <div class=\"flex items-center justify-between\">\n        <a href=\"#\" class=\"-m-1.5 p-1.5\">\n          <span class=\"sr-only\">Your Company</span>\n          <img class=\"h-8 w-auto\" src=\"https://tailwindui.com/img/logos/mark.svg?color=indigo&shade=600\" alt=\"\">\n        </a>\n        <button type=\"button\" class=\"-m-2.5 rounded-md p-2.5 text-gray-700\">\n          <span class=\"sr-only\">Close menu</span>\n          <svg class=\"h-6 w-6\" fill=\"none\" viewBox=\"0 0 24 24\" stroke-width=\"1.5\" stroke=\"currentColor\" aria-hidden=\"true\">\n            <path stroke-linecap=\"round\" stroke-linejoin=\"round\" d=\"M6 18L18 6M6 6l12 12\" />\n          </svg>\n        </button>\n      </div>\n      <div class=\"mt-6 flow-root\">\n        <div class=\"-my-6 divide-y divide-gray-500/10\">\n          <div class=\"space-y-2 py-6\">\n            <div class=\"-mx-3\">\n              <button type=\"button\" class=\"flex w-full items-center justify-between rounded-lg py-2 pl-3 pr-3.5 text-base font-semibold leading-7 text-gray-900 hover:bg-gray-50\" aria-controls=\"disclosure-1\" aria-expanded=\"false\">\n                Product\n                <!--\n                  Expand/collapse icon, toggle classes based on menu open state.\n\n                  Open: \"rotate-180\", Closed: \"\"\n                -->\n                <svg class=\"h-5 w-5 flex-none\" viewBox=\"0 0 20 20\" fill=\"currentColor\" aria-hidden=\"true\">\n                  <path fill-rule=\"evenodd\" d=\"M5.23 7.21a.75.75 0 011.06.02L10 11.168l3.71-3.938a.75.75 0 111.08 1.04l-4.25 4.5a.75.75 0 01-1.08 0l-4.25-4.5a.75.75 0 01.02-1.06z\" clip-rule=\"evenodd\" />\n                </svg>\n              </button>\n              <!-- 'Product' sub-menu, show/hide based on menu state. -->\n              <div class=\"mt-2 space-y-2\" id=\"disclosure-1\">\n                <a href=\"#\" class=\"block rounded-lg py-2 pl-6 pr-3 text-sm font-semibold leading-7 text-gray-900 hover:bg-gray-50\">Analytics</a>\n                <a href=\"#\" class=\"block rounded-lg py-2 pl-6 pr-3 text-sm font-semibold leading-7 text-gray-900 hover:bg-gray-50\">Engagement</a>\n                <a href=\"#\" class=\"block rounded-lg py-2 pl-6 pr-3 text-sm font-semibold leading-7 text-gray-900 hover:bg-gray-50\">Security</a>\n                <a href=\"#\" class=\"block rounded-lg py-2 pl-6 pr-3 text-sm font-semibold leading-7 text-gray-900 hover:bg-gray-50\">Integrations</a>\n                <a href=\"#\" class=\"block rounded-lg py-2 pl-6 pr-3 text-sm font-semibold leading-7 text-gray-900 hover:bg-gray-50\">Automations</a>\n                <a href=\"#\" class=\"block rounded-lg py-2 pl-6 pr-3 text-sm font-semibold leading-7 text-gray-900 hover:bg-gray-50\">Watch demo</a>\n                <a href=\"#\" class=\"block rounded-lg py-2 pl-6 pr-3 text-sm font-semibold leading-7 text-gray-900 hover:bg-gray-50\">Contact sales</a>\n              </div>\n            </div>\n            <a href=\"#\" class=\"-mx-3 block rounded-lg px-3 py-2 text-base font-semibold leading-7 text-gray-900 hover:bg-gray-50\">Features</a>\n            <a href=\"#\" class=\"-mx-3 block rounded-lg px-3 py-2 text-base font-semibold leading-7 text-gray-900 hover:bg-gray-50\">Marketplace</a>\n            <a href=\"#\" class=\"-mx-3 block rounded-lg px-3 py-2 text-base font-semibold leading-7 text-gray-900 hover:bg-gray-50\">Company</a>\n          </div>\n          <div class=\"py-6\">\n            <a href=\"#\" class=\"-mx-3 block rounded-lg px-3 py-2.5 text-base font-semibold leading-7 text-gray-900 hover:bg-gray-50\">Log in</a>\n          </div>\n        </div>\n      </div>\n    </div>\n  </div>\n</header>\n",
    "html": "<header class=\"bg-white\">\n  <nav class=\"mx-auto flex max-w-7xl items-center justify-between p-6 lg:px-8\" aria-label=\"Global\">\n    <div class=\"flex lg:flex-1\">\n      <a href=\"#\" class=\"-m-1.5 p-1.5\">\n        <span class=\"sr-only\">Your Company</span>\n        <img class=\"h-8 w-auto\" src=\"https://tailwindui.com/img/logos/mark.svg?color=indigo&shade=600\" alt=\"\">\n      </a>\n    </div>\n    <div class=\"flex lg:hidden\">\n      <button type=\"button\" class=\"-m-2.5 inline-flex items-center justify-center rounded-md p-2.5 text-gray-700\">\n        <span class=\"sr-only\">Open main menu</span>\n        <svg class=\"h-6 w-6\" fill=\"none\" viewBox=\"0 0 24 24\" stroke-width=\"1.5\" stroke=\"currentColor\" aria-hidden=\"true\">\n          <path stroke-linecap=\"round\" stroke-linejoin=\"round\" d=\"M3.75 6.75h16.5M3.75 12h16.5m-16.5 5.25h16.5\" />\n        </svg>\n      </button>\n    </div>\n    <div class=\"hidden lg:flex lg:gap-x-12\">\n      <div class=\"relative\">\n        <button type=\"button\" class=\"flex items-center gap-x-1 text-sm font-semibold leading-6 text-gray-900\" aria-expanded=\"false\">\n          Product\n          <svg class=\"h-5 w-5 flex-none text-gray-400\" viewBox=\"0 0 20 20\" fill=\"currentColor\" aria-hidden=\"true\">\n            <path fill-rule=\"evenodd\" d=\"M5.23 7.21a.75.75 0 011.06.02L10 11.168l3.71-3.938a.75.75 0 111.08 1.04l-4.25 4.5a.75.75 0 01-1.08 0l-4.25-4.5a.75.75 0 01.02-1.06z\" clip-rule=\"evenodd\" />\n          </svg>\n        </button>\n\n        <!--\n          'Product' flyout menu, show/hide based on flyout menu state.\n\n          Entering: \"transition ease-out duration-200\"\n            From: \"opacity-0 translate-y-1\"\n            To: \"opacity-100 translate-y-0\"\n          Leaving: \"transition ease-in duration-150\"\n            From: \"opacity-100 translate-y-0\"\n            To: \"opacity-0 translate-y-1\"\n        -->\n        <div class=\"absolute -left-8 top-full z-10 mt-3 w-screen max-w-md overflow-hidden rounded-3xl bg-white shadow-lg ring-1 ring-gray-900/5\">\n          <div class=\"p-4\">\n            <div class=\"group relative flex items-center gap-x-6 rounded-lg p-4 text-sm leading-6 hover:bg-gray-50\">\n              <div class=\"flex h-11 w-11 flex-none items-center justify-center rounded-lg bg-gray-50 group-hover:bg-white\">\n                <svg class=\"h-6 w-6 text-gray-600 group-hover:text-indigo-600\" fill=\"none\" viewBox=\"0 0 24 24\" stroke-width=\"1.5\" stroke=\"currentColor\" aria-hidden=\"true\">\n                  <path stroke-linecap=\"round\" stroke-linejoin=\"round\" d=\"M10.5 6a7.5 7.5 0 107.5 7.5h-7.5V6z\" />\n                  <path stroke-linecap=\"round\" stroke-linejoin=\"round\" d=\"M13.5 10.5H21A7.5 7.5 0 0013.5 3v7.5z\" />\n                </svg>\n              </div>\n              <div class=\"flex-auto\">\n                <a href=\"#\" class=\"block font-semibold text-gray-900\">\n                  Analytics\n                  <span class=\"absolute inset-0\"></span>\n                </a>\n                <p class=\"mt-1 text-gray-600\">Get a better understanding of your traffic</p>\n              </div>\n            </div>\n            <div class=\"group relative flex items-center gap-x-6 rounded-lg p-4 text-sm leading-6 hover:bg-gray-50\">\n              <div class=\"flex h-11 w-11 flex-none items-center justify-center rounded-lg bg-gray-50 group-hover:bg-white\">\n                <svg class=\"h-6 w-6 text-gray-600 group-hover:text-indigo-600\" fill=\"none\" viewBox=\"0 0 24 24\" stroke-width=\"1.5\" stroke=\"currentColor\" aria-hidden=\"true\">\n                  <path stroke-linecap=\"round\" stroke-linejoin=\"round\" d=\"M15.042 21.672L13.684 16.6m0 0l-2.51 2.225.569-9.47 5.227 7.917-3.286-.672zM12 2.25V4.5m5.834.166l-1.591 1.591M20.25 10.5H18M7.757 14.743l-1.59 1.59M6 10.5H3.75m4.007-4.243l-1.59-1.59\" />\n                </svg>\n              </div>\n              <div class=\"flex-auto\">\n                <a href=\"#\" class=\"block font-semibold text-gray-900\">\n                  Engagement\n                  <span class=\"absolute inset-0\"></span>\n                </a>\n                <p class=\"mt-1 text-gray-600\">Speak directly to your customers</p>\n              </div>\n            </div>\n            <div class=\"group relative flex items-center gap-x-6 rounded-lg p-4 text-sm leading-6 hover:bg-gray-50\">\n              <div class=\"flex h-11 w-11 flex-none items-center justify-center rounded-lg bg-gray-50 group-hover:bg-white\">\n                <svg class=\"h-6 w-6 text-gray-600 group-hover:text-indigo-600\" fill=\"none\" viewBox=\"0 0 24 24\" stroke-width=\"1.5\" stroke=\"currentColor\" aria-hidden=\"true\">\n                  <path stroke-linecap=\"round\" stroke-linejoin=\"round\" d=\"M7.864 4.243A7.5 7.5 0 0119.5 10.5c0 2.92-.556 5.709-1.568 8.268M5.742 6.364A7.465 7.465 0 004.5 10.5a7.464 7.464 0 01-1.15 3.993m1.989 3.559A11.209 11.209 0 008.25 10.5a3.75 3.75 0 117.5 0c0 .527-.021 1.049-.064 1.565M12 10.5a14.94 14.94 0 01-3.6 9.75m6.633-4.596a18.666 18.666 0 01-2.485 5.33\" />\n                </svg>\n              </div>\n              <div class=\"flex-auto\">\n                <a href=\"#\" class=\"block font-semibold text-gray-900\">\n                  Security\n                  <span class=\"absolute inset-0\"></span>\n                </a>\n                <p class=\"mt-1 text-gray-600\">Your customers’ data will be safe and secure</p>\n              </div>\n            </div>\n            <div class=\"group relative flex items-center gap-x-6 rounded-lg p-4 text-sm leading-6 hover:bg-gray-50\">\n              <div class=\"flex h-11 w-11 flex-none items-center justify-center rounded-lg bg-gray-50 group-hover:bg-white\">\n                <svg class=\"h-6 w-6 text-gray-600 group-hover:text-indigo-600\" fill=\"none\" viewBox=\"0 0 24 24\" stroke-width=\"1.5\" stroke=\"currentColor\" aria-hidden=\"true\">\n                  <path stroke-linecap=\"round\" stroke-linejoin=\"round\" d=\"M13.5 16.875h3.375m0 0h3.375m-3.375 0V13.5m0 3.375v3.375M6 10.5h2.25a2.25 2.25 0 002.25-2.25V6a2.25 2.25 0 00-2.25-2.25H6A2.25 2.25 0 003.75 6v2.25A2.25 2.25 0 006 10.5zm0 9.75h2.25A2.25 2.25 0 0010.5 18v-2.25a2.25 2.25 0 00-2.25-2.25H6a2.25 2.25 0 00-2.25 2.25V18A2.25 2.25 0 006 20.25zm9.75-9.75H18a2.25 2.25 0 002.25-2.25V6A2.25 2.25 0 0018 3.75h-2.25A2.25 2.25 0 0013.5 6v2.25a2.25 2.25 0 002.25 2.25z\" />\n                </svg>\n              </div>\n              <div class=\"flex-auto\">\n                <a href=\"#\" class=\"block font-semibold text-gray-900\">\n                  Integrations\n                  <span class=\"absolute inset-0\"></span>\n                </a>\n                <p class=\"mt-1 text-gray-600\">Connect with third-party tools</p>\n              </div>\n            </div>\n            <div class=\"group relative flex items-center gap-x-6 rounded-lg p-4 text-sm leading-6 hover:bg-gray-50\">\n              <div class=\"flex h-11 w-11 flex-none items-center justify-center rounded-lg bg-gray-50 group-hover:bg-white\">\n                <svg class=\"h-6 w-6 text-gray-600 group-hover:text-indigo-600\" fill=\"none\" viewBox=\"0 0 24 24\" stroke-width=\"1.5\" stroke=\"currentColor\" aria-hidden=\"true\">\n                  <path stroke-linecap=\"round\" stroke-linejoin=\"round\" d=\"M16.023 9.348h4.992v-.001M2.985 19.644v-4.992m0 0h4.992m-4.993 0l3.181 3.183a8.25 8.25 0 0013.803-3.7M4.031 9.865a8.25 8.25 0 0113.803-3.7l3.181 3.182m0-4.991v4.99\" />\n                </svg>\n              </div>\n              <div class=\"flex-auto\">\n                <a href=\"#\" class=\"block font-semibold text-gray-900\">\n                  Automations\n                  <span class=\"absolute inset-0\"></span>\n                </a>\n                <p class=\"mt-1 text-gray-600\">Build strategic funnels that will convert</p>\n              </div>\n            </div>\n          </div>\n          <div class=\"grid grid-cols-2 divide-x divide-gray-900/5 bg-gray-50\">\n            <a href=\"#\" class=\"flex items-center justify-center gap-x-2.5 p-3 text-sm font-semibold leading-6 text-gray-900 hover:bg-gray-100\">\n              <svg class=\"h-5 w-5 flex-none text-gray-400\" viewBox=\"0 0 20 20\" fill=\"currentColor\" aria-hidden=\"true\">\n                <path fill-rule=\"evenodd\" d=\"M2 10a8 8 0 1116 0 8 8 0 01-16 0zm6.39-2.908a.75.75 0 01.766.027l3.5 2.25a.75.75 0 010 1.262l-3.5 2.25A.75.75 0 018 12.25v-4.5a.75.75 0 01.39-.658z\" clip-rule=\"evenodd\" />\n              </svg>\n              Watch demo\n            </a>\n            <a href=\"#\" class=\"flex items-center justify-center gap-x-2.5 p-3 text-sm font-semibold leading-6 text-gray-900 hover:bg-gray-100\">\n              <svg class=\"h-5 w-5 flex-none text-gray-400\" viewBox=\"0 0 20 20\" fill=\"currentColor\" aria-hidden=\"true\">\n                <path fill-rule=\"evenodd\" d=\"M2 3.5A1.5 1.5 0 013.5 2h1.148a1.5 1.5 0 011.465 1.175l.716 3.223a1.5 1.5 0 01-1.052 1.767l-.933.267c-.41.117-.643.555-.48.95a11.542 11.542 0 006.254 6.254c.395.163.833-.07.95-.48l.267-.933a1.5 1.5 0 011.767-1.052l3.223.716A1.5 1.5 0 0118 15.352V16.5a1.5 1.5 0 01-1.5 1.5H15c-1.149 0-2.263-.15-3.326-.43A13.022 13.022 0 012.43 8.326 13.019 13.019 0 012 5V3.5z\" clip-rule=\"evenodd\" />\n              </svg>\n              Contact sales\n            </a>\n          </div>\n        </div>\n      </div>\n\n      <a href=\"#\" class=\"text-sm font-semibold leading-6 text-gray-900\">Features</a>\n      <a href=\"#\" class=\"text-sm font-semibold leading-6 text-gray-900\">Marketplace</a>\n      <a href=\"#\" class=\"text-sm font-semibold leading-6 text-gray-900\">Company</a>\n    </div>\n    <div class=\"hidden lg:flex lg:flex-1 lg:justify-end\">\n      <a href=\"#\" class=\"text-sm font-semibold leading-6 text-gray-900\">Log in <span aria-hidden=\"true\">&rarr;</span></a>\n    </div>\n  </nav>\n  <!-- Mobile menu, show/hide based on menu open state. -->\n  <div class=\"lg:hidden\" role=\"dialog\" aria-modal=\"true\">\n    <!-- Background backdrop, show/hide based on slide-over state. -->\n    <div class=\"fixed inset-0 z-10\"></div>\n    <div class=\"fixed inset-y-0 right-0 z-10 w-full overflow-y-auto bg-white px-6 py-6 sm:max-w-sm sm:ring-1 sm:ring-gray-900/10\">\n      <div class=\"flex items-center justify-between\">\n        <a href=\"#\" class=\"-m-1.5 p-1.5\">\n          <span class=\"sr-only\">Your Company</span>\n          <img class=\"h-8 w-auto\" src=\"https://tailwindui.com/img/logos/mark.svg?color=indigo&shade=600\" alt=\"\">\n        </a>\n        <button type=\"button\" class=\"-m-2.5 rounded-md p-2.5 text-gray-700\">\n          <span class=\"sr-only\">Close menu</span>\n          <svg class=\"h-6 w-6\" fill=\"none\" viewBox=\"0 0 24 24\" stroke-width=\"1.5\" stroke=\"currentColor\" aria-hidden=\"true\">\n            <path stroke-linecap=\"round\" stroke-linejoin=\"round\" d=\"M6 18L18 6M6 6l12 12\" />\n          </svg>\n        </button>\n      </div>\n      <div class=\"mt-6 flow-root\">\n        <div class=\"-my-6 divide-y divide-gray-500/10\">\n          <div class=\"space-y-2 py-6\">\n            <div class=\"-mx-3\">\n              <button type=\"button\" class=\"flex w-full items-center justify-between rounded-lg py-2 pl-3 pr-3.5 text-base font-semibold leading-7 text-gray-900 hover:bg-gray-50\" aria-controls=\"disclosure-1\" aria-expanded=\"false\">\n                Product\n                <!--\n                  Expand/collapse icon, toggle classes based on menu open state.\n\n                  Open: \"rotate-180\", Closed: \"\"\n                -->\n                <svg class=\"h-5 w-5 flex-none\" viewBox=\"0 0 20 20\" fill=\"currentColor\" aria-hidden=\"true\">\n                  <path fill-rule=\"evenodd\" d=\"M5.23 7.21a.75.75 0 011.06.02L10 11.168l3.71-3.938a.75.75 0 111.08 1.04l-4.25 4.5a.75.75 0 01-1.08 0l-4.25-4.5a.75.75 0 01.02-1.06z\" clip-rule=\"evenodd\" />\n                </svg>\n              </button>\n              <!-- 'Product' sub-menu, show/hide based on menu state. -->\n              <div class=\"mt-2 space-y-2\" id=\"disclosure-1\">\n                <a href=\"#\" class=\"block rounded-lg py-2 pl-6 pr-3 text-sm font-semibold leading-7 text-gray-900 hover:bg-gray-50\">Analytics</a>\n                <a href=\"#\" class=\"block rounded-lg py-2 pl-6 pr-3 text-sm font-semibold leading-7 text-gray-900 hover:bg-gray-50\">Engagement</a>\n                <a href=\"#\" class=\"block rounded-lg py-2 pl-6 pr-3 text-sm font-semibold leading-7 text-gray-900 hover:bg-gray-50\">Security</a>\n                <a href=\"#\" class=\"block rounded-lg py-2 pl-6 pr-3 text-sm font-semibold leading-7 text-gray-900 hover:bg-gray-50\">Integrations</a>\n                <a href=\"#\" class=\"block rounded-lg py-2 pl-6 pr-3 text-sm font-semibold leading-7 text-gray-900 hover:bg-gray-50\">Automations</a>\n                <a href=\"#\" class=\"block rounded-lg py-2 pl-6 pr-3 text-sm font-semibold leading-7 text-gray-900 hover:bg-gray-50\">Watch demo</a>\n                <a href=\"#\" class=\"block rounded-lg py-2 pl-6 pr-3 text-sm font-semibold leading-7 text-gray-900 hover:bg-gray-50\">Contact sales</a>\n              </div>\n            </div>\n            <a href=\"#\" class=\"-mx-3 block rounded-lg px-3 py-2 text-base font-semibold leading-7 text-gray-900 hover:bg-gray-50\">Features</a>\n            <a href=\"#\" class=\"-mx-3 block rounded-lg px-3 py-2 text-base font-semibold leading-7 text-gray-900 hover:bg-gray-50\">Marketplace</a>\n            <a href=\"#\" class=\"-mx-3 block rounded-lg px-3 py-2 text-base font-semibold leading-7 text-gray-900 hover:bg-gray-50\">Company</a>\n          </div>\n          <div class=\"py-6\">\n            <a href=\"#\" class=\"-mx-3 block rounded-lg px-3 py-2.5 text-base font-semibold leading-7 text-gray-900 hover:bg-gray-50\">Log in</a>\n          </div>\n        </div>\n      </div>\n    </div>\n  </div>\n</header>\n"
  },
  {
    "info": {
      "name": "header1",
      "type": "header"
    },
    "use": "<%- include(common_component + '/header/header1.ejs')%>",
    "ejs": "<div class=\"\">\n  <div class=\"bg-gray-200\">\n    <div class=\"flex flex-wrap items-center h-8 leading-8 gap-3 max_width\">\n      <svg xmlns=\"http://www.w3.org/2000/svg\" width=\"1em\" height=\"1em\" viewBox=\"0 0 24 24\">\n        <path fill=\"currentColor\" d=\"M21 10.12h-6.78l2.74-2.82c-2.73-2.7-7.15-2.8-9.88-.1c-2.73 2.71-2.73 7.08 0 9.79s7.15 2.71 9.88 0C18.32 15.65 19 14.08 19 12.1h2c0 1.98-.88 4.55-2.64 6.29c-3.51 3.48-9.21 3.48-12.72 0c-3.5-3.47-3.53-9.11-.02-12.58s9.14-3.47 12.65 0L21 3zM12.5 8v4.25l3.5 2.08l-.72 1.21L11 13V8z\" />\n      </svg> <span id=\"h-date-text\" class=\"text-[12px]\">Saturday, October 7</span>\n    </div>\n  </div>\n  <div class=\"max_width py-5 justify-between flex\">\n    <ul class=\"hidden md:flex gap-3\">\n      <% channelList.forEach((item, index) => { %>\n      <li><a href=\"<%= item.htmlName %>\"><%=item.name%></a></li>\n      <% }) %>\n    </ul>\n    <a href=\"\" class=\"font-bold text-xl\">\n      <%=email%>\n    </a>\n    <div class=\"hidden md:flex w-fit px-5 border-1 bg-gray-200\">\n      <input class=\"bg-transparent\" type=\"text\" placeholder=\"Search...\">\n      <svg xmlns=\"http://www.w3.org/2000/svg\" width=\"1em\" height=\"1em\" viewBox=\"0 0 26 26\">\n        <path fill=\"currentColor\" d=\"M10 .188A9.812 9.812 0 0 0 .187 10A9.812 9.812 0 0 0 10 19.813c2.29 0 4.393-.811 6.063-2.125l.875.875a1.845 1.845 0 0 0 .343 2.156l4.594 4.625c.713.714 1.88.714 2.594 0l.875-.875a1.84 1.84 0 0 0 0-2.594l-4.625-4.594a1.824 1.824 0 0 0-2.157-.312l-.875-.875A9.812 9.812 0 0 0 10 .188M10 2a8 8 0 1 1 0 16a8 8 0 0 1 0-16M4.937 7.469a5.446 5.446 0 0 0-.812 2.875a5.46 5.46 0 0 0 5.469 5.469a5.516 5.516 0 0 0 3.156-1a7.166 7.166 0 0 1-.75.03a7.045 7.045 0 0 1-7.063-7.062c0-.104-.005-.208 0-.312\" />\n      </svg>\n    </div>\n  </div>\n</div>\n",
    "html": "<div class=\"\">\n  <div class=\"bg-gray-200\">\n    <div class=\"flex flex-wrap items-center h-8 leading-8 gap-3 max_width\">\n      <svg xmlns=\"http://www.w3.org/2000/svg\" width=\"1em\" height=\"1em\" viewBox=\"0 0 24 24\">\n        <path fill=\"currentColor\" d=\"M21 10.12h-6.78l2.74-2.82c-2.73-2.7-7.15-2.8-9.88-.1c-2.73 2.71-2.73 7.08 0 9.79s7.15 2.71 9.88 0C18.32 15.65 19 14.08 19 12.1h2c0 1.98-.88 4.55-2.64 6.29c-3.51 3.48-9.21 3.48-12.72 0c-3.5-3.47-3.53-9.11-.02-12.58s9.14-3.47 12.65 0L21 3zM12.5 8v4.25l3.5 2.08l-.72 1.21L11 13V8z\" />\n      </svg> <span id=\"h-date-text\" class=\"text-[12px]\">Saturday, October 7</span>\n    </div>\n  </div>\n  <div class=\"max_width py-5 justify-between flex\">\n    <ul class=\"hidden md:flex gap-3\">\n      \n      <li><a href=\"channel1.html\">Channel 1</a></li>\n      \n      <li><a href=\"channel2.html\">Channel 2</a></li>\n      \n      <li><a href=\"channel3.html\">Channel 3</a></li>\n      \n    </ul>\n    <a href=\"\" class=\"font-bold text-xl\">\n      website\n    </a>\n    <div class=\"hidden md:flex w-fit px-5 border-1 bg-gray-200\">\n      <input class=\"bg-transparent\" type=\"text\" placeholder=\"Search...\">\n      <svg xmlns=\"http://www.w3.org/2000/svg\" width=\"1em\" height=\"1em\" viewBox=\"0 0 26 26\">\n        <path fill=\"currentColor\" d=\"M10 .188A9.812 9.812 0 0 0 .187 10A9.812 9.812 0 0 0 10 19.813c2.29 0 4.393-.811 6.063-2.125l.875.875a1.845 1.845 0 0 0 .343 2.156l4.594 4.625c.713.714 1.88.714 2.594 0l.875-.875a1.84 1.84 0 0 0 0-2.594l-4.625-4.594a1.824 1.824 0 0 0-2.157-.312l-.875-.875A9.812 9.812 0 0 0 10 .188M10 2a8 8 0 1 1 0 16a8 8 0 0 1 0-16M4.937 7.469a5.446 5.446 0 0 0-.812 2.875a5.46 5.46 0 0 0 5.469 5.469a5.516 5.516 0 0 0 3.156-1a7.166 7.166 0 0 1-.75.03a7.045 7.045 0 0 1-7.063-7.062c0-.104-.005-.208 0-.312\" />\n      </svg>\n    </div>\n  </div>\n</div>\n"
  },
  {
    "info": {
      "name": "footer3",
      "type": "footer"
    },
    "use": "<%- include(common_component + '/footer/footer3.ejs')%>",
    "ejs": "<footer class=\"bg-gray-900 text-gray-300\">\n  <ul class=\"max_width flex gap-4 flex-row flex-wrap p-4 justify-center items-center text-center pb-28\">\n    <li>\n      <a href=\"./AboutUs.html\">About Us</a>\n    </li>\n    <li>\n      <a href=\"./PrivacyPolicy.html\">Privacy Policy</a>\n    </li>\n    <li>\n      <a href=\"./TermsofUse.html\">Terms of Use</a>\n    </li>\n    <li class=\"w-full text-2xl font-bold text-white\">\n      <%=email%>.com\n    </li>\n    <li class=\"w-full\">\n      Copyright 2019 - 2024\n    </li>\n\n  </ul>\n</footer>\n",
    "html": "<footer class=\"bg-gray-900 text-gray-300\">\n  <ul class=\"max_width flex gap-4 flex-row flex-wrap p-4 justify-center items-center text-center pb-28\">\n    <li>\n      <a href=\"./AboutUs.html\">About Us</a>\n    </li>\n    <li>\n      <a href=\"./PrivacyPolicy.html\">Privacy Policy</a>\n    </li>\n    <li>\n      <a href=\"./TermsofUse.html\">Terms of Use</a>\n    </li>\n    <li class=\"w-full text-2xl font-bold text-white\">\n      website.com\n    </li>\n    <li class=\"w-full\">\n      Copyright 2019 - 2024\n    </li>\n\n  </ul>\n</footer>\n"
  },
  {
    "info": {
      "name": "footer2",
      "type": "footer"
    },
    "use": "<%- include(common_component + '/footer/footer2.ejs')%>",
    "ejs": "\n\n<footer class=\"bg-white rounded-lg shadow m-4 dark:bg-gray-800\">\n  <div class=\"w-full mx-auto max-w-screen-xl p-4 md:flex md:items-center md:justify-between\">\n    <span class=\"text-sm text-gray-500 sm:text-center dark:text-gray-400\">© Copyright 2019 - 2024 <%=email%>.com\n    </span>\n    <ul class=\"flex flex-wrap items-center mt-3 text-sm font-medium text-gray-500 dark:text-gray-400 sm:mt-0\">\n      <li>\n        <a href=\"./AboutUs.html\" class=\"hover:underline me-4 md:me-6\">About Us</a>\n      </li>\n      <li>\n        <a href=\"./PrivacyPolicy.html\" class=\"hover:underline me-4 md:me-6\">Privacy Policy</a>\n      </li>\n      <li>\n        <a href=\"./TermsofUse.html\" class=\"hover:underline me-4 md:me-6\">Terms of Use</a>\n      </li>\n    </ul>\n  </div>\n</footer>\n",
    "html": "\n\n<footer class=\"bg-white rounded-lg shadow m-4 dark:bg-gray-800\">\n  <div class=\"w-full mx-auto max-w-screen-xl p-4 md:flex md:items-center md:justify-between\">\n    <span class=\"text-sm text-gray-500 sm:text-center dark:text-gray-400\">© Copyright 2019 - 2024 website.com\n    </span>\n    <ul class=\"flex flex-wrap items-center mt-3 text-sm font-medium text-gray-500 dark:text-gray-400 sm:mt-0\">\n      <li>\n        <a href=\"./AboutUs.html\" class=\"hover:underline me-4 md:me-6\">About Us</a>\n      </li>\n      <li>\n        <a href=\"./PrivacyPolicy.html\" class=\"hover:underline me-4 md:me-6\">Privacy Policy</a>\n      </li>\n      <li>\n        <a href=\"./TermsofUse.html\" class=\"hover:underline me-4 md:me-6\">Terms of Use</a>\n      </li>\n    </ul>\n  </div>\n</footer>\n"
  },
  {
    "info": {
      "name": "footer1",
      "type": "footer"
    },
    "use": "<%- include(common_component + '/footer/footer1.ejs')%>",
    "ejs": "<footer class=\"bg-green-700 text-white\">\n  <ul class=\"max_width flex gap-2 flex-row flex-wrap p-4 justify-center items-center text-center pb-28\">\n    <li>\n      <a href=\"./AboutUs.html\">About Us</a>\n    </li>\n    <li>\n      <a href=\"./PrivacyPolicy.html\">Privacy Policy</a>\n    </li>\n    <li>\n      <a href=\"./TermsofUse.html\">Terms of Use</a>\n    </li>\n    <li class=\"w-full\">\n      Copyright 2019 - 2024\n    </li>\n    <li class=\"w-full text-2xl font-bold\">\n      <%=email%>.com\n    </li>\n  </ul>\n</footer>\n",
    "html": "<footer class=\"bg-green-700 text-white\">\n  <ul class=\"max_width flex gap-2 flex-row flex-wrap p-4 justify-center items-center text-center pb-28\">\n    <li>\n      <a href=\"./AboutUs.html\">About Us</a>\n    </li>\n    <li>\n      <a href=\"./PrivacyPolicy.html\">Privacy Policy</a>\n    </li>\n    <li>\n      <a href=\"./TermsofUse.html\">Terms of Use</a>\n    </li>\n    <li class=\"w-full\">\n      Copyright 2019 - 2024\n    </li>\n    <li class=\"w-full text-2xl font-bold\">\n      website.com\n    </li>\n  </ul>\n</footer>\n"
  },
  {
    "info": {
      "name": "card9",
      "type": "card"
    },
    "use": "<%- include(common_component + '/card/card9.ejs' , {item, hide:{description: true}})%>",
    "ejs": "<a href=\"<%=item.html_url ? item.html_url : item.id%>.html\" class=\"flex gap-2 h-full overflow-hidden\">\n  <img class=\"w-2/5 object-cover object-center\" data-src=\"<%=prefix%><%=item.picture%>\" alt=\"blog\">\n  <div class=\"flex-1\">\n    <p class=\"text-[12px] text-teal-600 mb-2\">\n      <span class=\"iconfont icon-jilu text-[12px]\"></span>  <span><%=item.time%></span>\n    </p>\n    <h1 class=\"title-font text-sm font-bold text-gray-900 mb-2 line-clamp-2\"><%=item.subtitle?item.subtitle:item.main_title%></h1>\n  </div>\n</a>\n",
    "html": "<a href=\"romantic-road-trips-from-chennai-to-ooty.html\" class=\"flex gap-2 h-full overflow-hidden\">\n  <img class=\"w-2/5 object-cover object-center\" data-src=\"https://image.jiafengfmc.cn/file/35219d5c41f8afd9b5ffc.png\" alt=\"blog\">\n  <div class=\"flex-1\">\n    <p class=\"text-[12px] text-teal-600 mb-2\">\n      <span class=\"iconfont icon-jilu text-[12px]\"></span>  <span>Dec 25, 2023</span>\n    </p>\n    <h1 class=\"title-font text-sm font-bold text-gray-900 mb-2 line-clamp-2\">Gluten-Free Diet: A Guide On Foods, Benefits, And Diet Plan</h1>\n  </div>\n</a>\n"
  },
  {
    "info": {
      "name": "card8",
      "type": "card"
    },
    "use": "<%- include(common_component + '/card/card8.ejs' , {item, hide:{description: true}})%>",
    "ejs": "<a href=\"<%=item.html_url ? item.html_url : item.id%>.html\" class=\"h-full overflow-hidden\">\n  <img class=\"w-full object-cover object-center\" data-src=\"<%=prefix%><%=item.picture%>\" alt=\"blog\">\n  <div class=\"pt-4\">\n    <h1 class=\"title-font text-lg font-bold text-gray-900 mb-2 line-clamp-1\"><%=item.subtitle?item.subtitle:item.main_title%></h1>\n    <p class=\"text-sm text-teal-600 mb-2\">\n     <span class=\"iconfont icon-jilu text-sm\"></span> <span><%=item.time%></span>\n    </p>\n    <p class=\"leading-relaxed mb-4 line-clamp-3 <%=hide.description ? 'hidden' : ''%>\"><%=item.description%></p>\n  </div>\n</a>\n",
    "html": "<a href=\"romantic-road-trips-from-chennai-to-ooty.html\" class=\"h-full overflow-hidden\">\n  <img class=\"w-full object-cover object-center\" data-src=\"https://image.jiafengfmc.cn/file/632794ec49126a0f0de77.png\" alt=\"blog\">\n  <div class=\"pt-4\">\n    <h1 class=\"title-font text-lg font-bold text-gray-900 mb-2 line-clamp-1\">Gluten-Free Diet: A Guide On Foods, Benefits, And Diet Plan</h1>\n    <p class=\"text-sm text-teal-600 mb-2\">\n     <span class=\"iconfont icon-jilu text-sm\"></span> <span>Dec 25, 2023</span>\n    </p>\n    <p class=\"leading-relaxed mb-4 line-clamp-3 hidden\">Explore the charm of romance while traveling the picturesque route from Chennai to Ooty. Discover magnificent scenery and make priceless memories.</p>\n  </div>\n</a>\n"
  },
  {
    "info": {
      "name": "card7",
      "type": "card"
    },
    "use": "<%- include(common_component + '/card/card7.ejs' , {item, hide:{description: true}})%>",
    "ejs": "  <div class=\"p-4\">\n    <a href=\"<%=item.html_url ? item.html_url : item.id%>.html\" class=\"h-full overflow-hidden\">\n      <img class=\"lg:h-48 md:h-36 w-full object-cover object-center\" data-src=\"<%=prefix%><%=item.picture%>\" alt=\"blog\">\n      <div class=\"py-6\">\n        <h2 class=\"text-xs w-fit rounded-sm text-white px-3 py-1 bg-pink-600 mb-2\"><%=item.name%></h2>\n        <h1 class=\"title-font text-lg font-medium text-gray-900 mb-2 line-clamp-1\"><%=item.subtitle?item.subtitle:item.main_title%></h1>\n        <p class=\"text-sm text-gray-500 mb-2\">\n          <span><%=item.time%></span> By <%=item.username%>\n        </p>\n        <p class=\"leading-relaxed mb-4 line-clamp-3\"><%=item.description%></p>\n        <div class=\"px-2 w-fit border border-solid border-black\">\n          Read More\n        </div>\n      </div>\n    </a>\n  </div>\n",
    "html": "  <div class=\"p-4\">\n    <a href=\"romantic-road-trips-from-chennai-to-ooty.html\" class=\"h-full overflow-hidden\">\n      <img class=\"lg:h-48 md:h-36 w-full object-cover object-center\" data-src=\"https://image.jiafengfmc.cn/file/af0b29f917017d303b7ee.png\" alt=\"blog\">\n      <div class=\"py-6\">\n        <h2 class=\"text-xs w-fit rounded-sm text-white px-3 py-1 bg-pink-600 mb-2\">Destinations</h2>\n        <h1 class=\"title-font text-lg font-medium text-gray-900 mb-2 line-clamp-1\">Gluten-Free Diet: A Guide On Foods, Benefits, And Diet Plan</h1>\n        <p class=\"text-sm text-gray-500 mb-2\">\n          <span>Dec 25, 2023</span> By Sean William\n        </p>\n        <p class=\"leading-relaxed mb-4 line-clamp-3\">Explore the charm of romance while traveling the picturesque route from Chennai to Ooty. Discover magnificent scenery and make priceless memories.</p>\n        <div class=\"px-2 w-fit border border-solid border-black\">\n          Read More\n        </div>\n      </div>\n    </a>\n  </div>\n"
  },
  {
    "info": {
      "name": "card6",
      "type": "card"
    },
    "use": "<%- include(common_component + '/card/card6.ejs' , {item, hide:{description: true}})%>",
    "ejs": "  <div class=\"p-4\">\n    <div class=\"h-full border-2 border-gray-200 border-opacity-60 rounded-lg overflow-hidden\">\n      <img class=\"lg:h-48 md:h-36 w-full object-cover object-center\" data-src=\"<%=prefix%><%=item.picture%>\" alt=\"blog\">\n      <div class=\"p-6\">\n        <h2 class=\"tracking-widest text-xs title-font font-medium text-gray-500 mb-1\"><%=item.name%></h2>\n        <h1 class=\"title-font text-lg font-medium text-gray-900 mb-3 line-clamp-1\"><%=item.subtitle?item.subtitle:item.main_title%></h1>\n        <p class=\"leading-relaxed mb-3 line-clamp-3\"><%=item.description%></p>\n        <div class=\"flex items-center flex-wrap \">\n          <a href=\"<%=item.html_url ? item.html_url : item.id%>.html\" class=\"text-indigo-500 py-4 inline-flex items-center md:mb-2 lg:mb-0\">Learn More\n            <svg class=\"w-4 h-4 ml-2\" viewBox=\"0 0 24 24\" stroke=\"currentColor\" stroke-width=\"2\" fill=\"none\" stroke-linecap=\"round\" stroke-linejoin=\"round\">\n              <path d=\"M5 12h14\"></path>\n              <path d=\"M12 5l7 7-7 7\"></path>\n            </svg>\n          </a>\n          <span class=\"text-gray-400 mr-3 inline-flex items-center lg:ml-auto md:ml-0 ml-auto leading-none text-sm pr-3 py-1 border-r-2 border-gray-200\">\n            <svg class=\"w-4 h-4 mr-1\" stroke=\"currentColor\" stroke-width=\"2\" fill=\"none\" stroke-linecap=\"round\" stroke-linejoin=\"round\" viewBox=\"0 0 24 24\">\n              <path d=\"M1 12s4-8 11-8 11 8 11 8-4 8-11 8-11-8-11-8z\"></path>\n              <circle cx=\"12\" cy=\"12\" r=\"3\"></circle>\n            </svg>20K\n          </span>\n          <span class=\"text-gray-400 inline-flex items-center leading-none text-sm\">\n            <svg xmlns=\"http://www.w3.org/2000/svg\" width=\"1em\" height=\"1em\" viewBox=\"0 0 24 24\">\n              <path fill=\"currentColor\" d=\"m20.975 12.185l-.739-.128zm-.705 4.08l-.74-.128zM6.938 20.477l-.747.065zm-.812-9.393l.747-.064zm7.869-5.863l.74.122zm-.663 4.045l.74.121zm-6.634.411l-.49-.568zm1.439-1.24l.49.569zm2.381-3.653l-.726-.189zm.476-1.834l.726.188zm1.674-.886l-.23.714zm.145.047l.229-.714zM9.862 6.463l.662.353zm4.043-3.215l-.726.188zm-2.23-1.116l-.326-.675zM3.971 21.471l-.748.064zM3 10.234l.747-.064a.75.75 0 0 0-1.497.064zm17.236 1.823l-.705 4.08l1.478.256l.705-4.08zm-6.991 9.193H8.596v1.5h4.649zm-5.56-.837l-.812-9.393l-1.495.129l.813 9.393zm11.846-4.276c-.507 2.93-3.15 5.113-6.286 5.113v1.5c3.826 0 7.126-2.669 7.764-6.357zM13.255 5.1l-.663 4.045l1.48.242l.663-4.044zm-6.067 5.146l1.438-1.24l-.979-1.136L6.21 9.11zm4.056-5.274l.476-1.834l-1.452-.376l-.476 1.833zm1.194-2.194l.145.047l.459-1.428l-.145-.047zm-1.915 4.038a8.378 8.378 0 0 0 .721-1.844l-1.452-.377A6.878 6.878 0 0 1 9.2 6.11zm2.06-3.991a.885.885 0 0 1 .596.61l1.452-.376a2.385 2.385 0 0 0-1.589-1.662zm-.863.313a.515.515 0 0 1 .28-.33l-.651-1.351c-.532.256-.932.73-1.081 1.305zm.28-.33a.596.596 0 0 1 .438-.03l.459-1.428a2.096 2.096 0 0 0-1.548.107zm2.154 8.176h5.18v-1.5h-5.18zM4.719 21.406L3.747 10.17l-1.494.129l.971 11.236zm-.969.107V10.234h-1.5v11.279zm-.526.022a.263.263 0 0 1 .263-.285v1.5c.726 0 1.294-.622 1.232-1.344zM14.735 5.343a5.533 5.533 0 0 0-.104-2.284l-1.452.377a4.03 4.03 0 0 1 .076 1.664zM8.596 21.25a.916.916 0 0 1-.911-.837l-1.494.129a2.416 2.416 0 0 0 2.405 2.208zm.03-12.244c.68-.586 1.413-1.283 1.898-2.19L9.2 6.109c-.346.649-.897 1.196-1.553 1.76zm13.088 3.307a2.416 2.416 0 0 0-2.38-2.829v1.5c.567 0 1 .512.902 1.073zM3.487 21.25c.146 0 .263.118.263.263h-1.5c0 .682.553 1.237 1.237 1.237zm9.105-12.105a1.583 1.583 0 0 0 1.562 1.84v-1.5a.083.083 0 0 1-.082-.098zm-5.72 1.875a.918.918 0 0 1 .316-.774l-.98-1.137a2.418 2.418 0 0 0-.83 2.04z\" />\n            </svg>20K\n          </span>\n        </div>\n      </div>\n    </div>\n  </div>\n",
    "html": "  <div class=\"p-4\">\n    <div class=\"h-full border-2 border-gray-200 border-opacity-60 rounded-lg overflow-hidden\">\n      <img class=\"lg:h-48 md:h-36 w-full object-cover object-center\" data-src=\"https://image.jiafengfmc.cn/file/35219d5c41f8afd9b5ffc.png\" alt=\"blog\">\n      <div class=\"p-6\">\n        <h2 class=\"tracking-widest text-xs title-font font-medium text-gray-500 mb-1\">Destinations</h2>\n        <h1 class=\"title-font text-lg font-medium text-gray-900 mb-3 line-clamp-1\">Gluten-Free Diet: A Guide On Foods, Benefits, And Diet Plan</h1>\n        <p class=\"leading-relaxed mb-3 line-clamp-3\">Explore the charm of romance while traveling the picturesque route from Chennai to Ooty. Discover magnificent scenery and make priceless memories.</p>\n        <div class=\"flex items-center flex-wrap \">\n          <a href=\"romantic-road-trips-from-chennai-to-ooty.html\" class=\"text-indigo-500 py-4 inline-flex items-center md:mb-2 lg:mb-0\">Learn More\n            <svg class=\"w-4 h-4 ml-2\" viewBox=\"0 0 24 24\" stroke=\"currentColor\" stroke-width=\"2\" fill=\"none\" stroke-linecap=\"round\" stroke-linejoin=\"round\">\n              <path d=\"M5 12h14\"></path>\n              <path d=\"M12 5l7 7-7 7\"></path>\n            </svg>\n          </a>\n          <span class=\"text-gray-400 mr-3 inline-flex items-center lg:ml-auto md:ml-0 ml-auto leading-none text-sm pr-3 py-1 border-r-2 border-gray-200\">\n            <svg class=\"w-4 h-4 mr-1\" stroke=\"currentColor\" stroke-width=\"2\" fill=\"none\" stroke-linecap=\"round\" stroke-linejoin=\"round\" viewBox=\"0 0 24 24\">\n              <path d=\"M1 12s4-8 11-8 11 8 11 8-4 8-11 8-11-8-11-8z\"></path>\n              <circle cx=\"12\" cy=\"12\" r=\"3\"></circle>\n            </svg>20K\n          </span>\n          <span class=\"text-gray-400 inline-flex items-center leading-none text-sm\">\n            <svg xmlns=\"http://www.w3.org/2000/svg\" width=\"1em\" height=\"1em\" viewBox=\"0 0 24 24\">\n              <path fill=\"currentColor\" d=\"m20.975 12.185l-.739-.128zm-.705 4.08l-.74-.128zM6.938 20.477l-.747.065zm-.812-9.393l.747-.064zm7.869-5.863l.74.122zm-.663 4.045l.74.121zm-6.634.411l-.49-.568zm1.439-1.24l.49.569zm2.381-3.653l-.726-.189zm.476-1.834l.726.188zm1.674-.886l-.23.714zm.145.047l.229-.714zM9.862 6.463l.662.353zm4.043-3.215l-.726.188zm-2.23-1.116l-.326-.675zM3.971 21.471l-.748.064zM3 10.234l.747-.064a.75.75 0 0 0-1.497.064zm17.236 1.823l-.705 4.08l1.478.256l.705-4.08zm-6.991 9.193H8.596v1.5h4.649zm-5.56-.837l-.812-9.393l-1.495.129l.813 9.393zm11.846-4.276c-.507 2.93-3.15 5.113-6.286 5.113v1.5c3.826 0 7.126-2.669 7.764-6.357zM13.255 5.1l-.663 4.045l1.48.242l.663-4.044zm-6.067 5.146l1.438-1.24l-.979-1.136L6.21 9.11zm4.056-5.274l.476-1.834l-1.452-.376l-.476 1.833zm1.194-2.194l.145.047l.459-1.428l-.145-.047zm-1.915 4.038a8.378 8.378 0 0 0 .721-1.844l-1.452-.377A6.878 6.878 0 0 1 9.2 6.11zm2.06-3.991a.885.885 0 0 1 .596.61l1.452-.376a2.385 2.385 0 0 0-1.589-1.662zm-.863.313a.515.515 0 0 1 .28-.33l-.651-1.351c-.532.256-.932.73-1.081 1.305zm.28-.33a.596.596 0 0 1 .438-.03l.459-1.428a2.096 2.096 0 0 0-1.548.107zm2.154 8.176h5.18v-1.5h-5.18zM4.719 21.406L3.747 10.17l-1.494.129l.971 11.236zm-.969.107V10.234h-1.5v11.279zm-.526.022a.263.263 0 0 1 .263-.285v1.5c.726 0 1.294-.622 1.232-1.344zM14.735 5.343a5.533 5.533 0 0 0-.104-2.284l-1.452.377a4.03 4.03 0 0 1 .076 1.664zM8.596 21.25a.916.916 0 0 1-.911-.837l-1.494.129a2.416 2.416 0 0 0 2.405 2.208zm.03-12.244c.68-.586 1.413-1.283 1.898-2.19L9.2 6.109c-.346.649-.897 1.196-1.553 1.76zm13.088 3.307a2.416 2.416 0 0 0-2.38-2.829v1.5c.567 0 1 .512.902 1.073zM3.487 21.25c.146 0 .263.118.263.263h-1.5c0 .682.553 1.237 1.237 1.237zm9.105-12.105a1.583 1.583 0 0 0 1.562 1.84v-1.5a.083.083 0 0 1-.082-.098zm-5.72 1.875a.918.918 0 0 1 .316-.774l-.98-1.137a2.418 2.418 0 0 0-.83 2.04z\" />\n            </svg>20K\n          </span>\n        </div>\n      </div>\n    </div>\n  </div>\n"
  },
  {
    "info": {
      "name": "card5",
      "type": "card"
    },
    "use": "<%- include(common_component + '/card/card5.ejs' , {item, hide:{description: true}})%>",
    "ejs": "<div class=\"p-4\">\n  <img class=\"rounded-t-lg w-full\" alt=\"\" data-src=\"<%=prefix%><%=item.picture%>\">\n  <div class=\"bg-zinc-50 bg-opacity-75 px-8 pt-10 pb-10 rounded-lg overflow-hidden text-center relative\">\n    <h2 class=\"tracking-widest text-xs title-font font-medium text-gray-500 mb-1\"><%=item.name%></h2>\n    <h1 class=\"title-font sm:text-2xl text-xl font-medium text-gray-900 mb-3 line-clamp-1\"><%=item.main_title%></h1>\n    <p class=\"leading-relaxed mb-3 line-clamp-3\"><%=item.description%></p>\n    <a href=\"<%=item.html_url ? item.html_url : item.id%>.html\" class=\"text-indigo-500 py-4 inline-flex items-center\">Learn More\n      <svg class=\"w-4 h-4 ml-2\" viewBox=\"0 0 24 24\" stroke=\"currentColor\" stroke-width=\"2\" fill=\"none\" stroke-linecap=\"round\" stroke-linejoin=\"round\">\n        <path d=\"M5 12h14\"></path>\n        <path d=\"M12 5l7 7-7 7\"></path>\n      </svg>\n    </a>\n    <div class=\"text-center mt-2 leading-none flex justify-center absolute bottom-0 left-0 w-full py-4\">\n      <span class=\"text-gray-400 mr-3 inline-flex items-center leading-none text-sm pr-3 py-1 border-r-2 border-gray-200\">\n        <svg class=\"w-4 h-4 mr-1\" stroke=\"currentColor\" stroke-width=\"2\" fill=\"none\" stroke-linecap=\"round\" stroke-linejoin=\"round\" viewBox=\"0 0 24 24\">\n          <path d=\"M1 12s4-8 11-8 11 8 11 8-4 8-11 8-11-8-11-8z\"></path>\n          <circle cx=\"12\" cy=\"12\" r=\"3\"></circle>\n        </svg>2.4K\n      </span>\n      <span class=\"text-gray-400 inline-flex items-center leading-none text-sm\">\n        <svg xmlns=\"http://www.w3.org/2000/svg\" width=\"1em\" height=\"1em\" viewBox=\"0 0 24 24\">\n          <path fill=\"currentColor\" d=\"m20.975 12.185l-.739-.128zm-.705 4.08l-.74-.128zM6.938 20.477l-.747.065zm-.812-9.393l.747-.064zm7.869-5.863l.74.122zm-.663 4.045l.74.121zm-6.634.411l-.49-.568zm1.439-1.24l.49.569zm2.381-3.653l-.726-.189zm.476-1.834l.726.188zm1.674-.886l-.23.714zm.145.047l.229-.714zM9.862 6.463l.662.353zm4.043-3.215l-.726.188zm-2.23-1.116l-.326-.675zM3.971 21.471l-.748.064zM3 10.234l.747-.064a.75.75 0 0 0-1.497.064zm17.236 1.823l-.705 4.08l1.478.256l.705-4.08zm-6.991 9.193H8.596v1.5h4.649zm-5.56-.837l-.812-9.393l-1.495.129l.813 9.393zm11.846-4.276c-.507 2.93-3.15 5.113-6.286 5.113v1.5c3.826 0 7.126-2.669 7.764-6.357zM13.255 5.1l-.663 4.045l1.48.242l.663-4.044zm-6.067 5.146l1.438-1.24l-.979-1.136L6.21 9.11zm4.056-5.274l.476-1.834l-1.452-.376l-.476 1.833zm1.194-2.194l.145.047l.459-1.428l-.145-.047zm-1.915 4.038a8.378 8.378 0 0 0 .721-1.844l-1.452-.377A6.878 6.878 0 0 1 9.2 6.11zm2.06-3.991a.885.885 0 0 1 .596.61l1.452-.376a2.385 2.385 0 0 0-1.589-1.662zm-.863.313a.515.515 0 0 1 .28-.33l-.651-1.351c-.532.256-.932.73-1.081 1.305zm.28-.33a.596.596 0 0 1 .438-.03l.459-1.428a2.096 2.096 0 0 0-1.548.107zm2.154 8.176h5.18v-1.5h-5.18zM4.719 21.406L3.747 10.17l-1.494.129l.971 11.236zm-.969.107V10.234h-1.5v11.279zm-.526.022a.263.263 0 0 1 .263-.285v1.5c.726 0 1.294-.622 1.232-1.344zM14.735 5.343a5.533 5.533 0 0 0-.104-2.284l-1.452.377a4.03 4.03 0 0 1 .076 1.664zM8.596 21.25a.916.916 0 0 1-.911-.837l-1.494.129a2.416 2.416 0 0 0 2.405 2.208zm.03-12.244c.68-.586 1.413-1.283 1.898-2.19L9.2 6.109c-.346.649-.897 1.196-1.553 1.76zm13.088 3.307a2.416 2.416 0 0 0-2.38-2.829v1.5c.567 0 1 .512.902 1.073zM3.487 21.25c.146 0 .263.118.263.263h-1.5c0 .682.553 1.237 1.237 1.237zm9.105-12.105a1.583 1.583 0 0 0 1.562 1.84v-1.5a.083.083 0 0 1-.082-.098zm-5.72 1.875a.918.918 0 0 1 .316-.774l-.98-1.137a2.418 2.418 0 0 0-.83 2.04z\"></path>\n        </svg>9.9K\n      </span>\n    </div>\n  </div>\n</div>\n",
    "html": "<div class=\"p-4\">\n  <img class=\"rounded-t-lg w-full\" alt=\"\" data-src=\"https://image.jiafengfmc.cn/file/e762a0c7ea10035b0a3ae.png\">\n  <div class=\"bg-zinc-50 bg-opacity-75 px-8 pt-10 pb-10 rounded-lg overflow-hidden text-center relative\">\n    <h2 class=\"tracking-widest text-xs title-font font-medium text-gray-500 mb-1\">Destinations</h2>\n    <h1 class=\"title-font sm:text-2xl text-xl font-medium text-gray-900 mb-3 line-clamp-1\">Gluten-Free Diet: A Guide On Foods, Benefits, And Diet Plan</h1>\n    <p class=\"leading-relaxed mb-3 line-clamp-3\">Explore the charm of romance while traveling the picturesque route from Chennai to Ooty. Discover magnificent scenery and make priceless memories.</p>\n    <a href=\"romantic-road-trips-from-chennai-to-ooty.html\" class=\"text-indigo-500 py-4 inline-flex items-center\">Learn More\n      <svg class=\"w-4 h-4 ml-2\" viewBox=\"0 0 24 24\" stroke=\"currentColor\" stroke-width=\"2\" fill=\"none\" stroke-linecap=\"round\" stroke-linejoin=\"round\">\n        <path d=\"M5 12h14\"></path>\n        <path d=\"M12 5l7 7-7 7\"></path>\n      </svg>\n    </a>\n    <div class=\"text-center mt-2 leading-none flex justify-center absolute bottom-0 left-0 w-full py-4\">\n      <span class=\"text-gray-400 mr-3 inline-flex items-center leading-none text-sm pr-3 py-1 border-r-2 border-gray-200\">\n        <svg class=\"w-4 h-4 mr-1\" stroke=\"currentColor\" stroke-width=\"2\" fill=\"none\" stroke-linecap=\"round\" stroke-linejoin=\"round\" viewBox=\"0 0 24 24\">\n          <path d=\"M1 12s4-8 11-8 11 8 11 8-4 8-11 8-11-8-11-8z\"></path>\n          <circle cx=\"12\" cy=\"12\" r=\"3\"></circle>\n        </svg>2.4K\n      </span>\n      <span class=\"text-gray-400 inline-flex items-center leading-none text-sm\">\n        <svg xmlns=\"http://www.w3.org/2000/svg\" width=\"1em\" height=\"1em\" viewBox=\"0 0 24 24\">\n          <path fill=\"currentColor\" d=\"m20.975 12.185l-.739-.128zm-.705 4.08l-.74-.128zM6.938 20.477l-.747.065zm-.812-9.393l.747-.064zm7.869-5.863l.74.122zm-.663 4.045l.74.121zm-6.634.411l-.49-.568zm1.439-1.24l.49.569zm2.381-3.653l-.726-.189zm.476-1.834l.726.188zm1.674-.886l-.23.714zm.145.047l.229-.714zM9.862 6.463l.662.353zm4.043-3.215l-.726.188zm-2.23-1.116l-.326-.675zM3.971 21.471l-.748.064zM3 10.234l.747-.064a.75.75 0 0 0-1.497.064zm17.236 1.823l-.705 4.08l1.478.256l.705-4.08zm-6.991 9.193H8.596v1.5h4.649zm-5.56-.837l-.812-9.393l-1.495.129l.813 9.393zm11.846-4.276c-.507 2.93-3.15 5.113-6.286 5.113v1.5c3.826 0 7.126-2.669 7.764-6.357zM13.255 5.1l-.663 4.045l1.48.242l.663-4.044zm-6.067 5.146l1.438-1.24l-.979-1.136L6.21 9.11zm4.056-5.274l.476-1.834l-1.452-.376l-.476 1.833zm1.194-2.194l.145.047l.459-1.428l-.145-.047zm-1.915 4.038a8.378 8.378 0 0 0 .721-1.844l-1.452-.377A6.878 6.878 0 0 1 9.2 6.11zm2.06-3.991a.885.885 0 0 1 .596.61l1.452-.376a2.385 2.385 0 0 0-1.589-1.662zm-.863.313a.515.515 0 0 1 .28-.33l-.651-1.351c-.532.256-.932.73-1.081 1.305zm.28-.33a.596.596 0 0 1 .438-.03l.459-1.428a2.096 2.096 0 0 0-1.548.107zm2.154 8.176h5.18v-1.5h-5.18zM4.719 21.406L3.747 10.17l-1.494.129l.971 11.236zm-.969.107V10.234h-1.5v11.279zm-.526.022a.263.263 0 0 1 .263-.285v1.5c.726 0 1.294-.622 1.232-1.344zM14.735 5.343a5.533 5.533 0 0 0-.104-2.284l-1.452.377a4.03 4.03 0 0 1 .076 1.664zM8.596 21.25a.916.916 0 0 1-.911-.837l-1.494.129a2.416 2.416 0 0 0 2.405 2.208zm.03-12.244c.68-.586 1.413-1.283 1.898-2.19L9.2 6.109c-.346.649-.897 1.196-1.553 1.76zm13.088 3.307a2.416 2.416 0 0 0-2.38-2.829v1.5c.567 0 1 .512.902 1.073zM3.487 21.25c.146 0 .263.118.263.263h-1.5c0 .682.553 1.237 1.237 1.237zm9.105-12.105a1.583 1.583 0 0 0 1.562 1.84v-1.5a.083.083 0 0 1-.082-.098zm-5.72 1.875a.918.918 0 0 1 .316-.774l-.98-1.137a2.418 2.418 0 0 0-.83 2.04z\"></path>\n        </svg>9.9K\n      </span>\n    </div>\n  </div>\n</div>\n"
  },
  {
    "info": {
      "name": "card4",
      "type": "card"
    },
    "use": "<%- include(common_component + '/card/card4.ejs' , {item, hide:{description: true}})%>",
    "ejs": "  <a href=\"<%=item.html_url ? item.html_url : item.id%>.html\" class=\"rounded overflow-hidden border-solid border-gray-400 border-2 block h-fit animate__animated  animate__fadeIn\">\n    <img class=\"w-full rounded-sm\" data-src=\"<%=prefix%><%=item.picture%>\" alt=\"Sunset in the mountains\">\n    <div class=\" p-2 flex flex-col justify-end text-center items-center\">\n      <div class=\"title-font sm:text-xl text-xl font-bold mb-3 line-clamp-2\">\n        <%=item.main_title%></div>\n      <div class=\"pb-2 text-xs flex\">\n        <svg xmlns=\"http://www.w3.org/2000/svg\" width=\"1.5em\" height=\"1.5em\" viewBox=\"0 0 24 24\"><path fill=\"currentColor\" d=\"M11 8.75v3.68c0 .35.19.68.49.86l3.12 1.85c.36.21.82.09 1.03-.26c.21-.36.1-.82-.26-1.03l-2.87-1.71v-3.4c-.01-.4-.35-.74-.76-.74s-.75.34-.75.75m10 .75V4.21c0-.45-.54-.67-.85-.35l-1.78 1.78a9.01 9.01 0 0 0-7.21-2.6c-4.19.38-7.64 3.75-8.1 7.94a9 9 0 0 0 17.87 2.14c.07-.6-.4-1.12-1-1.12c-.5 0-.92.37-.98.86c-.43 3.49-3.44 6.19-7.05 6.14c-3.71-.05-6.84-3.18-6.9-6.9C4.94 8.2 8.11 5 12 5c1.93 0 3.68.79 4.95 2.05l-2.09 2.09c-.32.32-.1.86.35.86h5.29c.28 0 .5-.22.5-.5\"/></svg>\n        <span class=\"ml-2\"><%=item.time%></span>\n      </div>\n      <div class=\"p-1 mb-2 line-clamp-2\">\n        <%=item.description%>\n      </div>\n    </div>\n  </a>\n",
    "html": "  <a href=\"romantic-road-trips-from-chennai-to-ooty.html\" class=\"rounded overflow-hidden border-solid border-gray-400 border-2 block h-fit animate__animated  animate__fadeIn\">\n    <img class=\"w-full rounded-sm\" data-src=\"https://image.jiafengfmc.cn/file/3d30901aee4d94a02d888.png\" alt=\"Sunset in the mountains\">\n    <div class=\" p-2 flex flex-col justify-end text-center items-center\">\n      <div class=\"title-font sm:text-xl text-xl font-bold mb-3 line-clamp-2\">\n        Gluten-Free Diet: A Guide On Foods, Benefits, And Diet Plan</div>\n      <div class=\"pb-2 text-xs flex\">\n        <svg xmlns=\"http://www.w3.org/2000/svg\" width=\"1.5em\" height=\"1.5em\" viewBox=\"0 0 24 24\"><path fill=\"currentColor\" d=\"M11 8.75v3.68c0 .35.19.68.49.86l3.12 1.85c.36.21.82.09 1.03-.26c.21-.36.1-.82-.26-1.03l-2.87-1.71v-3.4c-.01-.4-.35-.74-.76-.74s-.75.34-.75.75m10 .75V4.21c0-.45-.54-.67-.85-.35l-1.78 1.78a9.01 9.01 0 0 0-7.21-2.6c-4.19.38-7.64 3.75-8.1 7.94a9 9 0 0 0 17.87 2.14c.07-.6-.4-1.12-1-1.12c-.5 0-.92.37-.98.86c-.43 3.49-3.44 6.19-7.05 6.14c-3.71-.05-6.84-3.18-6.9-6.9C4.94 8.2 8.11 5 12 5c1.93 0 3.68.79 4.95 2.05l-2.09 2.09c-.32.32-.1.86.35.86h5.29c.28 0 .5-.22.5-.5\"/></svg>\n        <span class=\"ml-2\">Dec 25, 2023</span>\n      </div>\n      <div class=\"p-1 mb-2 line-clamp-2\">\n        Explore the charm of romance while traveling the picturesque route from Chennai to Ooty. Discover magnificent scenery and make priceless memories.\n      </div>\n    </div>\n  </a>\n"
  },
  {
    "info": {
      "name": "card3",
      "type": "card"
    },
    "use": "<%- include(common_component + '/card/card3.ejs' , {item, hide:{description: true}})%>",
    "ejs": "  <a href=\"<%=item.html_url ? item.html_url : item.id%>.html\" class=\" rounded overflow-hidden  h-60 sm:h-96  animate__animated  animate__fadeIn\">\n    <img class=\"w-full object-cover rounded-sm\" data-src=\"<%=prefix%><%=item.picture%>\" alt=\"Sunset in the mountains\">\n    <div class=\" p-2 flex flex-col justify-end\">\n      <div class=\"title-font sm:text-xl text-xl font-bold mb-3 line-clamp-2\">\n        <%=item.main_title%></div>\n      <div class=\"pb-2 text-xs mb-3\">\n        <i class=\"iconfont icon-jilu\"></i>\n        <%=item.time%>\n      </div>\n      <div class=\"title-font text-sm font-medium mb-3 text-gray-100/90 line-clamp-5 <%=hide.description ? 'hidden' : ''%>\">\n        <%=item.description%>\n      </div>\n      <div class=\"px-2 bg-yellow-400 text-white text-[13px] mb-2 w-fit\">\n        <%=item.name%>\n      </div>\n    </div>\n  </a>\n",
    "html": "  <a href=\"romantic-road-trips-from-chennai-to-ooty.html\" class=\" rounded overflow-hidden  h-60 sm:h-96  animate__animated  animate__fadeIn\">\n    <img class=\"w-full object-cover rounded-sm\" data-src=\"https://image.jiafengfmc.cn/file/3d30901aee4d94a02d888.png\" alt=\"Sunset in the mountains\">\n    <div class=\" p-2 flex flex-col justify-end\">\n      <div class=\"title-font sm:text-xl text-xl font-bold mb-3 line-clamp-2\">\n        Gluten-Free Diet: A Guide On Foods, Benefits, And Diet Plan</div>\n      <div class=\"pb-2 text-xs mb-3\">\n        <i class=\"iconfont icon-jilu\"></i>\n        Dec 25, 2023\n      </div>\n      <div class=\"title-font text-sm font-medium mb-3 text-gray-100/90 line-clamp-5 hidden\">\n        Explore the charm of romance while traveling the picturesque route from Chennai to Ooty. Discover magnificent scenery and make priceless memories.\n      </div>\n      <div class=\"px-2 bg-yellow-400 text-white text-[13px] mb-2 w-fit\">\n        Destinations\n      </div>\n    </div>\n  </a>\n"
  },
  {
    "info": {
      "name": "card20",
      "type": "card"
    },
    "use": "<%- include(common_component + '/card/card20.ejs' , {item, hide:{description: true}})%>",
    "ejs": "  <a href=\"<%=item.html_url ? item.html_url : item.id%>.html\" class=\"overflow-hidden relative inline-block animate__animated  animate__fadeIn\">\n    <img class=\"w-full h-full\" data-src=\"<%=prefix%><%=item.picture%>\" alt=\"Sunset in the mountains\">\n    <div class=\"absolute bottom-0 left-0 bg-gray-950/20 p-2 w-full h-full flex flex-col justify-end text-white\">\n      <div class=\"p-1 bg-red-500 mb-2 w-fit\">\n        <%=item.name%>\n      </div>\n      <div class=\"title-font sm:text-xl text-xl font-bold mb-3 line-clamp-2\">\n        <%=item.main_title%></div>\n      <div class=\"pb-2 text-xs\">\n        <i class=\"iconfont icon-jilu\"></i>\n        <%=item.time%>\n      </div>\n\n    </div>\n  </a>\n",
    "html": "  <a href=\"romantic-road-trips-from-chennai-to-ooty.html\" class=\"overflow-hidden relative inline-block animate__animated  animate__fadeIn\">\n    <img class=\"w-full h-full\" data-src=\"https://image.jiafengfmc.cn/file/3d30901aee4d94a02d888.png\" alt=\"Sunset in the mountains\">\n    <div class=\"absolute bottom-0 left-0 bg-gray-950/20 p-2 w-full h-full flex flex-col justify-end text-white\">\n      <div class=\"p-1 bg-red-500 mb-2 w-fit\">\n        Destinations\n      </div>\n      <div class=\"title-font sm:text-xl text-xl font-bold mb-3 line-clamp-2\">\n        Gluten-Free Diet: A Guide On Foods, Benefits, And Diet Plan</div>\n      <div class=\"pb-2 text-xs\">\n        <i class=\"iconfont icon-jilu\"></i>\n        Dec 25, 2023\n      </div>\n\n    </div>\n  </a>\n"
  },
  {
    "info": {
      "name": "card2",
      "type": "card"
    },
    "use": "<%- include(common_component + '/card/card2.ejs' , {item, hide:{description: true}})%>",
    "ejs": "  <a href=\"<%=item.html_url ? item.html_url : item.id%>.html\" class=\" rounded overflow-hidden relative inline-block h-60 sm:h-96  animate__animated  animate__fadeIn\">\n    <img class=\"w-full h-full rounded-sm\" data-src=\"<%=prefix%><%=item.picture%>\" alt=\"Sunset in the mountains\">\n    <div class=\"absolute bottom-0 left-0 bg-gray-950/20 p-2 w-full h-full flex flex-col justify-end text-white\">\n      <div class=\"title-font sm:text-xl text-xl font-bold mb-3 line-clamp-2\">\n        <%=item.main_title%></div>\n      <div class=\"pb-2 text-xs\">\n        <i class=\"iconfont icon-jilu\"></i>\n        <%=item.time%>\n      </div>\n      <div class=\"title-font text-sm font-medium mb-3 text-gray-100/90 line-clamp-5 <%=hide.description ? 'hidden' : ''%>\">\n        <%=item.description%>\n      </div>\n      <div class=\"absolute top-0 left-0 p-1 bg-yellow-400 mb-2\">\n        <%=item.name%>\n      </div>\n    </div>\n  </a>\n",
    "html": "  <a href=\"romantic-road-trips-from-chennai-to-ooty.html\" class=\" rounded overflow-hidden relative inline-block h-60 sm:h-96  animate__animated  animate__fadeIn\">\n    <img class=\"w-full h-full rounded-sm\" data-src=\"https://image.jiafengfmc.cn/file/632794ec49126a0f0de77.png\" alt=\"Sunset in the mountains\">\n    <div class=\"absolute bottom-0 left-0 bg-gray-950/20 p-2 w-full h-full flex flex-col justify-end text-white\">\n      <div class=\"title-font sm:text-xl text-xl font-bold mb-3 line-clamp-2\">\n        Gluten-Free Diet: A Guide On Foods, Benefits, And Diet Plan</div>\n      <div class=\"pb-2 text-xs\">\n        <i class=\"iconfont icon-jilu\"></i>\n        Dec 25, 2023\n      </div>\n      <div class=\"title-font text-sm font-medium mb-3 text-gray-100/90 line-clamp-5 hidden\">\n        Explore the charm of romance while traveling the picturesque route from Chennai to Ooty. Discover magnificent scenery and make priceless memories.\n      </div>\n      <div class=\"absolute top-0 left-0 p-1 bg-yellow-400 mb-2\">\n        Destinations\n      </div>\n    </div>\n  </a>\n"
  },
  {
    "info": {
      "name": "card19",
      "type": "card"
    },
    "use": "<%- include(common_component + '/card/card19.ejs' , {item, hide:{description: true}})%>",
    "ejs": "  <a href=\"<%-item.html_url ? item.html_url : item.id%>.html\" class=\"xl:flex xl:items-center lg:flex lg:items-center sm:flex sm:items-center gap-4\">\n    <img src=\"<%=prefix%><%=item.picture%>\" class=\"w-[100%] h-40 xl:w-60 xl:h-48 lg:w-52 lg:h-52 sm:w-52 sm:h-52\" />\n    <div class=\"w-full p-2 flex flex-col gap-2\">\n      <h1 class=\"font-bold line-clamp-2\"><%=item.subtitle?item.subtitle:item.main_title%></h1>\n      <div class=\"text-[12px] text-gray-400 flex items-center\">\n        <span class=\"iconfont icon-my text-[12px] mx-1\"></span>\n        <span><%=item.user_name%></span>\n        <span class=\"iconfont icon-jilu text-[12px]  ml-1\">\n        </span><%=item.time%>\n      </div>\n      <p class=\"text-gray-600 text-sm line-clamp-3\"><%=item.description%></p>\n      <div class=\"inline-block w-fit p-1 border border-solid text-sm border-gray-500 text-gray-500\">READ MORE</div>\n    </div>\n  </a>\n",
    "html": "  <a href=\"romantic-road-trips-from-chennai-to-ooty.html\" class=\"xl:flex xl:items-center lg:flex lg:items-center sm:flex sm:items-center gap-4\">\n    <img src=\"https://image.jiafengfmc.cn/file/35219d5c41f8afd9b5ffc.png\" class=\"w-[100%] h-40 xl:w-60 xl:h-48 lg:w-52 lg:h-52 sm:w-52 sm:h-52\" />\n    <div class=\"w-full p-2 flex flex-col gap-2\">\n      <h1 class=\"font-bold line-clamp-2\">Gluten-Free Diet: A Guide On Foods, Benefits, And Diet Plan</h1>\n      <div class=\"text-[12px] text-gray-400 flex items-center\">\n        <span class=\"iconfont icon-my text-[12px] mx-1\"></span>\n        <span></span>\n        <span class=\"iconfont icon-jilu text-[12px]  ml-1\">\n        </span>Dec 25, 2023\n      </div>\n      <p class=\"text-gray-600 text-sm line-clamp-3\">Explore the charm of romance while traveling the picturesque route from Chennai to Ooty. Discover magnificent scenery and make priceless memories.</p>\n      <div class=\"inline-block w-fit p-1 border border-solid text-sm border-gray-500 text-gray-500\">READ MORE</div>\n    </div>\n  </a>\n"
  },
  {
    "info": {
      "name": "card18",
      "type": "card"
    },
    "use": "<%- include(common_component + '/card/card18.ejs' , {item, hide:{description: true}})%>",
    "ejs": "<a href=\"<%=item.html_url ? item.html_url : item.id%>.html\" class=\"flex gap-2 h-full overflow-hidden\">\n  <img class=\"w-2/5 object-cover object-center\" data-src=\"<%=prefix%><%=item.picture%>\" alt=\"blog\">\n  <div class=\"flex-1\">\n    <h1 class=\"title-font font-bold text-gray-900 mb-2 line-clamp-2\"><%=item.subtitle?item.subtitle:item.main_title%></h1>\n    <p class=\"text-[12px] text-gray-500\">\n      <span class=\"iconfont icon-jilu text-[12px]\"></span> <span><%=item.time%></span>\n    </p>\n  </div>\n</a>\n",
    "html": "<a href=\"romantic-road-trips-from-chennai-to-ooty.html\" class=\"flex gap-2 h-full overflow-hidden\">\n  <img class=\"w-2/5 object-cover object-center\" data-src=\"https://image.jiafengfmc.cn/file/35219d5c41f8afd9b5ffc.png\" alt=\"blog\">\n  <div class=\"flex-1\">\n    <h1 class=\"title-font font-bold text-gray-900 mb-2 line-clamp-2\">Gluten-Free Diet: A Guide On Foods, Benefits, And Diet Plan</h1>\n    <p class=\"text-[12px] text-gray-500\">\n      <span class=\"iconfont icon-jilu text-[12px]\"></span> <span>Dec 25, 2023</span>\n    </p>\n  </div>\n</a>\n"
  },
  {
    "info": {
      "name": "card17",
      "type": "card"
    },
    "use": "<%- include(common_component + '/card/card17.ejs' , {item, hide:{description: true}})%>",
    "ejs": "  <a href=\"<%=item.html_url ? item.html_url : item.id%>.html\" class=\"h-fit relative overflow-hidden animate__animated  animate__fadeIn inline-block\">\n    <img class=\"w-full h-full\" data-src=\"<%=prefix%><%=item.picture%>\" alt=\"Sunset in the mountains\">\n    <div class=\"absolute bottom-0 left-0 bg-gray-950/30 p-2 text-center w-full h-full flex flex-col justify-end text-white\">\n      <div class=\"title-font sm:text-xl text-xl font-bold mb-3 line-clamp-2\">\n        <%=item.main_title%></div>\n      <div class=\"pb-2 text-xs\">\n        By <%=item.user_name%> <i class=\"iconfont icon-jilu\"></i> <span><%=item.time%></span>\n      </div>\n    </div>\n  </a>\n",
    "html": "  <a href=\"romantic-road-trips-from-chennai-to-ooty.html\" class=\"h-fit relative overflow-hidden animate__animated  animate__fadeIn inline-block\">\n    <img class=\"w-full h-full\" data-src=\"https://image.jiafengfmc.cn/file/3d30901aee4d94a02d888.png\" alt=\"Sunset in the mountains\">\n    <div class=\"absolute bottom-0 left-0 bg-gray-950/30 p-2 text-center w-full h-full flex flex-col justify-end text-white\">\n      <div class=\"title-font sm:text-xl text-xl font-bold mb-3 line-clamp-2\">\n        Gluten-Free Diet: A Guide On Foods, Benefits, And Diet Plan</div>\n      <div class=\"pb-2 text-xs\">\n        By  <i class=\"iconfont icon-jilu\"></i> <span>Dec 25, 2023</span>\n      </div>\n    </div>\n  </a>\n"
  },
  {
    "info": {
      "name": "card16",
      "type": "card"
    },
    "use": "<%- include(common_component + '/card/card16.ejs' , {item, hide:{description: true}})%>",
    "ejs": "<a href=\"<%=item.html_url ? item.html_url : item.id%>.html\" class=\"flex gap-2 h-full overflow-hidden\">\n  <img class=\"w-2/5 object-cover object-center\" data-src=\"<%=prefix%><%=item.picture%>\" alt=\"blog\">\n  <div class=\"flex-1\">\n    <h1 class=\"title-font text-sm font-bold text-gray-900 mb-2 line-clamp-3\"><%=item.subtitle?item.subtitle:item.main_title%></h1>\n    <p class=\"text-[12px] text-gray-500\">\n      <span class=\"iconfont icon-jilu text-[12px]\"></span> <span><%=item.time%></span>\n    </p>\n  </div>\n</a>\n",
    "html": "<a href=\"romantic-road-trips-from-chennai-to-ooty.html\" class=\"flex gap-2 h-full overflow-hidden\">\n  <img class=\"w-2/5 object-cover object-center\" data-src=\"https://image.jiafengfmc.cn/file/3d30901aee4d94a02d888.png\" alt=\"blog\">\n  <div class=\"flex-1\">\n    <h1 class=\"title-font text-sm font-bold text-gray-900 mb-2 line-clamp-3\">Gluten-Free Diet: A Guide On Foods, Benefits, And Diet Plan</h1>\n    <p class=\"text-[12px] text-gray-500\">\n      <span class=\"iconfont icon-jilu text-[12px]\"></span> <span>Dec 25, 2023</span>\n    </p>\n  </div>\n</a>\n"
  },
  {
    "info": {
      "name": "card15",
      "type": "card"
    },
    "use": "<%- include(common_component + '/card/card15.ejs' , {item, hide:{description: true}})%>",
    "ejs": "  <a href=\"<%-item.html_url ? item.html_url : item.id%>.html\" class=\"flex shadow-sm items-start\">\n    <div class=\"h-full w-1/3 relative inline\">\n      <img class=\"h-full\" src=\"<%=prefix%><%=item.picture%>\">\n      <div class=\"flex flex-col text-[12px] justify-center text-center text-gray-800 p-2 w-fit text-wrap bg-white absolute bottom-0 right-0\">\n        <span class=\"font-bold\">\n          <%=item.time.split(',')[0].split(' ')[1]%>\n        </span>\n        <span class=\"text-gray-600\">\n          <%=item.time.split(',')[0].split(' ')[0]%>\n        </span>\n      </div>\n    </div>\n    <div class=\"lex-1 p-3 flex-1 inline\">\n      <div class=\"inline-block p-1 mb-2 text-orange-700\"><%=item.name%></div>\n      <h1 class=\"text-lg font-bold line-clamp-2\"><%=item.subtitle?item.subtitle:item.main_title%></h1>\n    </div>\n  </a>\n",
    "html": "  <a href=\"romantic-road-trips-from-chennai-to-ooty.html\" class=\"flex shadow-sm items-start\">\n    <div class=\"h-full w-1/3 relative inline\">\n      <img class=\"h-full\" src=\"https://image.jiafengfmc.cn/file/8fba73267fd460122f4ce.png\">\n      <div class=\"flex flex-col text-[12px] justify-center text-center text-gray-800 p-2 w-fit text-wrap bg-white absolute bottom-0 right-0\">\n        <span class=\"font-bold\">\n          25\n        </span>\n        <span class=\"text-gray-600\">\n          Dec\n        </span>\n      </div>\n    </div>\n    <div class=\"lex-1 p-3 flex-1 inline\">\n      <div class=\"inline-block p-1 mb-2 text-orange-700\">Destinations</div>\n      <h1 class=\"text-lg font-bold line-clamp-2\">Gluten-Free Diet: A Guide On Foods, Benefits, And Diet Plan</h1>\n    </div>\n  </a>\n"
  },
  {
    "info": {
      "name": "card14",
      "type": "card"
    },
    "use": "<%- include(common_component + '/card/card14.ejs' , {item, hide:{description: true}})%>",
    "ejs": "  <a href=\"<%-item.html_url ? item.html_url : item.id%>.html\" class=\"xl:flex xl:items-center lg:flex lg:items-center sm:flex sm:items-center\">\n    <img src=\"<%=prefix%><%=item.picture%>\" class=\"w-[100%] h-40 xl:w-60 xl:h-48 lg:w-52 lg:h-52 sm:w-52 sm:h-52\" />\n    <div class=\"w-full p-2\">\n      <div class=\"inline-block p-1 mb-2 text-white bg-cyan-400 types\"><%=item.name%></div>\n      <h1 class=\"text-lg font-bold line-clamp-2\"><%=item.subtitle?item.subtitle:item.main_title%></h1>\n      <div class=\"my-2 text-sm text-gray-400\"><span class=\"iconfont icon-jilu\"></span><%=item.time%>\n      </div>\n      <p class=\"text-gray-600 line-clamp-3\"><%=item.description%></p>\n    </div>\n  </a>\n",
    "html": "  <a href=\"romantic-road-trips-from-chennai-to-ooty.html\" class=\"xl:flex xl:items-center lg:flex lg:items-center sm:flex sm:items-center\">\n    <img src=\"https://image.jiafengfmc.cn/file/f01e64e41151efc0e1ef9.png\" class=\"w-[100%] h-40 xl:w-60 xl:h-48 lg:w-52 lg:h-52 sm:w-52 sm:h-52\" />\n    <div class=\"w-full p-2\">\n      <div class=\"inline-block p-1 mb-2 text-white bg-cyan-400 types\">Destinations</div>\n      <h1 class=\"text-lg font-bold line-clamp-2\">Gluten-Free Diet: A Guide On Foods, Benefits, And Diet Plan</h1>\n      <div class=\"my-2 text-sm text-gray-400\"><span class=\"iconfont icon-jilu\"></span>Dec 25, 2023\n      </div>\n      <p class=\"text-gray-600 line-clamp-3\">Explore the charm of romance while traveling the picturesque route from Chennai to Ooty. Discover magnificent scenery and make priceless memories.</p>\n    </div>\n  </a>\n"
  },
  {
    "info": {
      "name": "card13",
      "type": "card"
    },
    "use": "<%- include(common_component + '/card/card13.ejs' , {item, hide:{description: true}})%>",
    "ejs": " <a href=\"<%-item.html_url ? item.html_url : item.id%>.html\" class=\"flex items-center relative\">\n   <img src=\"<%=prefix%><%=item.picture%>\" class=\"mr-3 xl:mr-6 w-28 h-28\" />\n   <div class=\"inline-block px-1 mb-2 text-white bg-cyan-400 py2 types absolute left-3 top-4\"><%=index+1%></div>\n   <div>\n     <div class=\"my-2 text-sm text-gray-400\"><span class=\"iconfont icon-jilu \"></span><%=item.time%>\n     </div>\n     <h1 class=\"line-clamp-2 font-bold\"><%=item.subtitle?item.subtitle:item.main_title%></h1>\n   </div>\n </a>\n",
    "html": " <a href=\"romantic-road-trips-from-chennai-to-ooty.html\" class=\"flex items-center relative\">\n   <img src=\"https://image.jiafengfmc.cn/file/f01e64e41151efc0e1ef9.png\" class=\"mr-3 xl:mr-6 w-28 h-28\" />\n   <div class=\"inline-block px-1 mb-2 text-white bg-cyan-400 py2 types absolute left-3 top-4\">3</div>\n   <div>\n     <div class=\"my-2 text-sm text-gray-400\"><span class=\"iconfont icon-jilu \"></span>Dec 25, 2023\n     </div>\n     <h1 class=\"line-clamp-2 font-bold\">Gluten-Free Diet: A Guide On Foods, Benefits, And Diet Plan</h1>\n   </div>\n </a>\n"
  },
  {
    "info": {
      "name": "card12",
      "type": "card"
    },
    "use": "<%- include(common_component + '/card/card12.ejs' , {item, hide:{description: true}})%>",
    "ejs": "<a href=\"<%-item.html_url ? item.html_url : item.id%>.html\">\n  <img src=\"<%=prefix%><%=item.picture%>\" class=\"w-full h-40 xl:h-56 sm:h-40\" />\n  <div class=\"w-full p-2\">\n    <div class=\"inline-block p-1 mb-2 text-white bg-cyan-400 types\"><%=item.name%></div>\n    <h1 class=\"text-lg lineFeed_2 font-bold\"><%=item.subtitle?item.subtitle:item.main_title%></h1>\n    <div class=\"my-2 text-sm text-gray-400\"><span class=\"iconfont icon-jilu \"></span><%=item.time%>\n    </div>\n    <p class=\"text-gray-600 line-clamp-3\"><%=item.description%></p>\n  </div>\n</a>\n",
    "html": "<a href=\"romantic-road-trips-from-chennai-to-ooty.html\">\n  <img src=\"https://image.jiafengfmc.cn/file/f01e64e41151efc0e1ef9.png\" class=\"w-full h-40 xl:h-56 sm:h-40\" />\n  <div class=\"w-full p-2\">\n    <div class=\"inline-block p-1 mb-2 text-white bg-cyan-400 types\">Destinations</div>\n    <h1 class=\"text-lg lineFeed_2 font-bold\">Gluten-Free Diet: A Guide On Foods, Benefits, And Diet Plan</h1>\n    <div class=\"my-2 text-sm text-gray-400\"><span class=\"iconfont icon-jilu \"></span>Dec 25, 2023\n    </div>\n    <p class=\"text-gray-600 line-clamp-3\">Explore the charm of romance while traveling the picturesque route from Chennai to Ooty. Discover magnificent scenery and make priceless memories.</p>\n  </div>\n</a>\n"
  },
  {
    "info": {
      "name": "card11",
      "type": "card"
    },
    "use": "<%- include(common_component + '/card/card11.ejs' , {item, hide:{description: true}})%>",
    "ejs": "<a href=\"<%-item.html_url ? item.html_url : item.id%>.html\" class=\"relative inline-block\">\n  <img src=\"<%=prefix%><%=item.picture%>\" class=\"w-full h-[250px] xl:h-96\" />\n  <div class=\"w-full p-4 bg-gray-950/60 absolute bottom-0\">\n    <div class=\"inline-block p-1 mb-2 text-sm text-white bg-cyan-400\"><%=item.name%></div>\n    <h1 class=\"text-[16px] text-white xl:text-lg font-bold line-clamp-2\"><%=item.subtitle?item.subtitle:item.main_title%></h1>\n  </div>\n</a>\n",
    "html": "<a href=\"romantic-road-trips-from-chennai-to-ooty.html\" class=\"relative inline-block\">\n  <img src=\"https://image.jiafengfmc.cn/file/b72a0e7d771482904ef9b.png\" class=\"w-full h-[250px] xl:h-96\" />\n  <div class=\"w-full p-4 bg-gray-950/60 absolute bottom-0\">\n    <div class=\"inline-block p-1 mb-2 text-sm text-white bg-cyan-400\">Destinations</div>\n    <h1 class=\"text-[16px] text-white xl:text-lg font-bold line-clamp-2\">Gluten-Free Diet: A Guide On Foods, Benefits, And Diet Plan</h1>\n  </div>\n</a>\n"
  },
  {
    "info": {
      "name": "card10",
      "type": "card"
    },
    "use": "<%- include(common_component + '/card/card10.ejs' , {item, hide:{description: true}})%>",
    "ejs": "  <div class=\"p-4\">\n    <a href=\"<%=item.html_url ? item.html_url : item.id%>.html\" class=\"h-full overflow-hidden\">\n      <img class=\"lg:h-48 md:h-36 w-full object-cover object-center\" data-src=\"<%=prefix%><%=item.picture%>\" alt=\"blog\">\n      <div class=\"py-6\">\n        <h2 class=\"text-xs w-fit rounded-sm text-white px-3 py-1 bg-pink-600 mb-2\"><%=item.name%></h2>\n        <h1 class=\"title-font text-lg font-medium text-gray-900 mb-2 line-clamp-1\"><%=item.subtitle?item.subtitle:item.main_title%></h1>\n        <p class=\"text-sm text-teal-600 mb-2\">\n          <span><%=item.time%></span> By <%=item.user_name%>\n        </p>\n        <p class=\"leading-relaxed mb-4 line-clamp-3\"><%=item.description%></p>\n        <div class=\"px-2 w-fit border border-solid border-black\">\n          Read More\n        </div>\n      </div>\n    </a>\n  </div>\n",
    "html": "  <div class=\"p-4\">\n    <a href=\"romantic-road-trips-from-chennai-to-ooty.html\" class=\"h-full overflow-hidden\">\n      <img class=\"lg:h-48 md:h-36 w-full object-cover object-center\" data-src=\"https://image.jiafengfmc.cn/file/35219d5c41f8afd9b5ffc.png\" alt=\"blog\">\n      <div class=\"py-6\">\n        <h2 class=\"text-xs w-fit rounded-sm text-white px-3 py-1 bg-pink-600 mb-2\">Destinations</h2>\n        <h1 class=\"title-font text-lg font-medium text-gray-900 mb-2 line-clamp-1\">Gluten-Free Diet: A Guide On Foods, Benefits, And Diet Plan</h1>\n        <p class=\"text-sm text-teal-600 mb-2\">\n          <span>Dec 25, 2023</span> By \n        </p>\n        <p class=\"leading-relaxed mb-4 line-clamp-3\">Explore the charm of romance while traveling the picturesque route from Chennai to Ooty. Discover magnificent scenery and make priceless memories.</p>\n        <div class=\"px-2 w-fit border border-solid border-black\">\n          Read More\n        </div>\n      </div>\n    </a>\n  </div>\n"
  },
  {
    "info": {
      "name": "card1",
      "type": "card"
    },
    "use": "<%- include(common_component + '/card/card1.ejs' , {item, hide:{description: true}})%>",
    "ejs": " <a href=\"<%=item.html_url ? item.html_url : item.id%>.html\" class=\"pb-2 overflow-hidden flex gap-2 border-b border-gray-500 border-solid animate__animated  animate__fadeIn\">\n   <img class=\"w-2/5 rounded-sm\" data-src=\"<%=prefix%><%=item.picture%>\" alt=\"Sunset in the mountains\">\n   <div class=\"flex-1\">\n     <div class=\"text-xs p-1 bg-green-500 w-fit mb-2\">\n       <%=item.name%>\n     </div>\n     <div class=\"title-font font-bold sm:text-sm text-sm  text-slate-600 mb-3 line-clamp-2\">\n       <%=item.main_title%>\n     </div>\n     <div class=\"title-font sm:text-sm text-sm font-medium text-gray-600 mb-3 line-clamp-3 <%=hide.description ? 'hidden' : ''%>\">\n       <%=item.description%>\n     </div>\n     <div class=\"pb-2 text-gray-500 text-xs\">\n       <i class=\"iconfont icon-jilu\"></i>\n       <%=item.time%>\n     </div>\n   </div>\n </a>\n",
    "html": " <a href=\"romantic-road-trips-from-chennai-to-ooty.html\" class=\"pb-2 overflow-hidden flex gap-2 border-b border-gray-500 border-solid animate__animated  animate__fadeIn\">\n   <img class=\"w-2/5 rounded-sm\" data-src=\"https://image.jiafengfmc.cn/file/632794ec49126a0f0de77.png\" alt=\"Sunset in the mountains\">\n   <div class=\"flex-1\">\n     <div class=\"text-xs p-1 bg-green-500 w-fit mb-2\">\n       Destinations\n     </div>\n     <div class=\"title-font font-bold sm:text-sm text-sm  text-slate-600 mb-3 line-clamp-2\">\n       Gluten-Free Diet: A Guide On Foods, Benefits, And Diet Plan\n     </div>\n     <div class=\"title-font sm:text-sm text-sm font-medium text-gray-600 mb-3 line-clamp-3 hidden\">\n       Explore the charm of romance while traveling the picturesque route from Chennai to Ooty. Discover magnificent scenery and make priceless memories.\n     </div>\n     <div class=\"pb-2 text-gray-500 text-xs\">\n       <i class=\"iconfont icon-jilu\"></i>\n       Dec 25, 2023\n     </div>\n   </div>\n </a>\n"
  }
]
